{
  "configVersion": 1,
  "timestamp": 1726690439833,
  "index": "/ar-SY/index.html",
  "assetGroups": [
    {
      "name": "app",
      "installMode": "prefetch",
      "updateMode": "prefetch",
      "cacheQueryOptions": {
        "ignoreVary": true
      },
      "urls": [
        "/ar-SY/chunk-27OSCRM5.js",
        "/ar-SY/chunk-2ARTI2XL.js",
        "/ar-SY/chunk-2AVMNSRR.js",
        "/ar-SY/chunk-2ESXI7NW.js",
        "/ar-SY/chunk-2OQBOLLM.js",
        "/ar-SY/chunk-2QBYFC2R.js",
        "/ar-SY/chunk-2RLRAFKW.js",
        "/ar-SY/chunk-3OTRSYK2.js",
        "/ar-SY/chunk-3TICWBDM.js",
        "/ar-SY/chunk-4BS7IIZZ.js",
        "/ar-SY/chunk-4WMX7V6I.js",
        "/ar-SY/chunk-56ONM2BK.js",
        "/ar-SY/chunk-5A24Y7FG.js",
        "/ar-SY/chunk-5KQRBASI.js",
        "/ar-SY/chunk-5TXOOLVZ.js",
        "/ar-SY/chunk-65XUGUD6.js",
        "/ar-SY/chunk-6H3FHWRN.js",
        "/ar-SY/chunk-6N6YXKEL.js",
        "/ar-SY/chunk-6YVLM3TN.js",
        "/ar-SY/chunk-6YXMS2BR.js",
        "/ar-SY/chunk-74QTK57S.js",
        "/ar-SY/chunk-77BL6AJT.js",
        "/ar-SY/chunk-7HVFJSX6.js",
        "/ar-SY/chunk-7MRZL6KI.js",
        "/ar-SY/chunk-7OTI4YDK.js",
        "/ar-SY/chunk-7TERTQEQ.js",
        "/ar-SY/chunk-7V34RKQI.js",
        "/ar-SY/chunk-A6EBSDLT.js",
        "/ar-SY/chunk-AIMGTUFT.js",
        "/ar-SY/chunk-ANO7OEOR.js",
        "/ar-SY/chunk-ASQTODNO.js",
        "/ar-SY/chunk-AXR3FHIB.js",
        "/ar-SY/chunk-B3FOEZVW.js",
        "/ar-SY/chunk-BHKXZLFS.js",
        "/ar-SY/chunk-BKQEWO4F.js",
        "/ar-SY/chunk-BOILL2JJ.js",
        "/ar-SY/chunk-BOX7CA7M.js",
        "/ar-SY/chunk-BU5743HF.js",
        "/ar-SY/chunk-BUKW6KC4.js",
        "/ar-SY/chunk-BYBGHJGR.js",
        "/ar-SY/chunk-C6G5FDC3.js",
        "/ar-SY/chunk-CFJSTZEI.js",
        "/ar-SY/chunk-CNHMU26L.js",
        "/ar-SY/chunk-COXKBNGP.js",
        "/ar-SY/chunk-CWSXRFA2.js",
        "/ar-SY/chunk-CXB7QISW.js",
        "/ar-SY/chunk-D6HKAENE.js",
        "/ar-SY/chunk-DDV3ZTDK.js",
        "/ar-SY/chunk-EIFEKQZ5.js",
        "/ar-SY/chunk-EVZ2FIK2.js",
        "/ar-SY/chunk-EY63G5JF.js",
        "/ar-SY/chunk-FTZQ2DLW.js",
        "/ar-SY/chunk-G2YTV5YP.js",
        "/ar-SY/chunk-GLKTSYN6.js",
        "/ar-SY/chunk-GM25OYN2.js",
        "/ar-SY/chunk-GVVLUNO3.js",
        "/ar-SY/chunk-H2P7XPBZ.js",
        "/ar-SY/chunk-HW5EUJLJ.js",
        "/ar-SY/chunk-IHCT72VP.js",
        "/ar-SY/chunk-IJU5IAB6.js",
        "/ar-SY/chunk-J3R4INTN.js",
        "/ar-SY/chunk-JFU4W3LU.js",
        "/ar-SY/chunk-JKWIZ5GL.js",
        "/ar-SY/chunk-JSCEI2V4.js",
        "/ar-SY/chunk-JSLQP7DR.js",
        "/ar-SY/chunk-K2OVNSCM.js",
        "/ar-SY/chunk-K2S4YDTN.js",
        "/ar-SY/chunk-K3CPYGZA.js",
        "/ar-SY/chunk-KELWJGI4.js",
        "/ar-SY/chunk-KEQWPQHD.js",
        "/ar-SY/chunk-LY65NDSL.js",
        "/ar-SY/chunk-M4AIK4I3.js",
        "/ar-SY/chunk-MG4IU3IR.js",
        "/ar-SY/chunk-MJWPWJKC.js",
        "/ar-SY/chunk-ML6BNME4.js",
        "/ar-SY/chunk-MQJH4F46.js",
        "/ar-SY/chunk-MQRGCQ3S.js",
        "/ar-SY/chunk-MS3W46DA.js",
        "/ar-SY/chunk-MXDHFMHH.js",
        "/ar-SY/chunk-MY6KCFOE.js",
        "/ar-SY/chunk-N3OI26PY.js",
        "/ar-SY/chunk-N4UNFT77.js",
        "/ar-SY/chunk-N6QQS7LB.js",
        "/ar-SY/chunk-NKXXNLKV.js",
        "/ar-SY/chunk-ODDAAWLR.js",
        "/ar-SY/chunk-P6UXWRH3.js",
        "/ar-SY/chunk-PER6NRC5.js",
        "/ar-SY/chunk-PM6FEDNM.js",
        "/ar-SY/chunk-PMOT4F4H.js",
        "/ar-SY/chunk-QQVDK5OV.js",
        "/ar-SY/chunk-RAM4WGO4.js",
        "/ar-SY/chunk-RHOUE5MX.js",
        "/ar-SY/chunk-RWLY27NV.js",
        "/ar-SY/chunk-S5NKVWMB.js",
        "/ar-SY/chunk-S7OYWSAY.js",
        "/ar-SY/chunk-SHFMPPN3.js",
        "/ar-SY/chunk-SJX7X5WF.js",
        "/ar-SY/chunk-SMEONY5R.js",
        "/ar-SY/chunk-SMSWA6Y3.js",
        "/ar-SY/chunk-TGGWUGCF.js",
        "/ar-SY/chunk-TKF7E2YR.js",
        "/ar-SY/chunk-U4N237WM.js",
        "/ar-SY/chunk-U72UV7FI.js",
        "/ar-SY/chunk-UA7SCKX3.js",
        "/ar-SY/chunk-UOJQ5IBE.js",
        "/ar-SY/chunk-VARUJZUG.js",
        "/ar-SY/chunk-VK6LNBMX.js",
        "/ar-SY/chunk-VOQPTL3E.js",
        "/ar-SY/chunk-VQ5NJNCO.js",
        "/ar-SY/chunk-VTI3DU76.js",
        "/ar-SY/chunk-W7FXRVMY.js",
        "/ar-SY/chunk-WDDGOVXW.js",
        "/ar-SY/chunk-WOGJSFX2.js",
        "/ar-SY/chunk-WX4XW32G.js",
        "/ar-SY/chunk-XYHX3JVK.js",
        "/ar-SY/chunk-Y6HRGFPG.js",
        "/ar-SY/chunk-YFTDYVS3.js",
        "/ar-SY/chunk-ZBZOYA56.js",
        "/ar-SY/chunk-ZCB5W4HJ.js",
        "/ar-SY/chunk-ZKMPTML6.js",
        "/ar-SY/chunk-ZLCKFGW7.js",
        "/ar-SY/chunk-ZONUYZGY.js",
        "/ar-SY/chunk-ZU4H4WCR.js",
        "/ar-SY/chunk-ZWRLN3HF.js",
        "/ar-SY/favicon.ico",
        "/ar-SY/index.html",
        "/ar-SY/main-YGXHIUDT.js",
        "/ar-SY/manifest.webmanifest",
        "/ar-SY/polyfills-EEFQP6KM.js",
        "/ar-SY/styles-JC6X7JJ2.css"
      ],
      "patterns": []
    },
    {
      "name": "assets",
      "installMode": "lazy",
      "updateMode": "prefetch",
      "cacheQueryOptions": {
        "ignoreVary": true
      },
      "urls": [
        "/ar-SY/assets/icons/icon-1024x1024.png",
        "/ar-SY/assets/icons/icon-128x128.png",
        "/ar-SY/assets/icons/icon-144x144.png",
        "/ar-SY/assets/icons/icon-152x152.png",
        "/ar-SY/assets/icons/icon-192x192.png",
        "/ar-SY/assets/icons/icon-384x384.png",
        "/ar-SY/assets/icons/icon-512x512.png",
        "/ar-SY/assets/icons/icon-72x72.png",
        "/ar-SY/assets/icons/icon-96x96.png",
        "/ar-SY/assets/icons/logo.svg",
        "/ar-SY/assets/routes.json",
        "/ar-SY/assets/silent-check-sso.html"
      ],
      "patterns": []
    }
  ],
  "dataGroups": [],
  "hashTable": {
    "/ar-SY/assets/icons/icon-1024x1024.png": "343f28cb3c76d72b107a2fefb10b969669c01be6",
    "/ar-SY/assets/icons/icon-128x128.png": "6fdefbdc892cf0a2e2978ec20c62adc78563ddcc",
    "/ar-SY/assets/icons/icon-144x144.png": "f5fa8ccd5a2f5446385359ed421392a3cb9a1f4c",
    "/ar-SY/assets/icons/icon-152x152.png": "75f380ad5e5402d022a212ae3b9fc8993c43bf28",
    "/ar-SY/assets/icons/icon-192x192.png": "8ee9e04e6f2c92021c43f6a4155c03d7b17a77cc",
    "/ar-SY/assets/icons/icon-384x384.png": "4e3fd5c70359fa04e2effad67fe75f5b97b0e267",
    "/ar-SY/assets/icons/icon-512x512.png": "0814ffa04b16bace18b263b5eaadf74ad93c66f8",
    "/ar-SY/assets/icons/icon-72x72.png": "f0c683910c6b082da8ad3f0b0a15cdc0011d3cf1",
    "/ar-SY/assets/icons/icon-96x96.png": "c7e674d0d4bec68e9690db445f3834848c61650e",
    "/ar-SY/assets/icons/logo.svg": "68e0aaf67e3dfda3fea05691634081ab400c0b19",
    "/ar-SY/assets/routes.json": "59902287b279810a236faa16df2e4fc779f41c01",
    "/ar-SY/assets/silent-check-sso.html": "245bcb1f39394815c4686c8f03820f8d52c46e9c",
    "/ar-SY/chunk-27OSCRM5.js": "63dcca0b45c565ee2ba9c2b5fe3381e4482aba20",
    "/ar-SY/chunk-2ARTI2XL.js": "45aef3fcebdf42de13e1d7d672492b4f8aaac76f",
    "/ar-SY/chunk-2AVMNSRR.js": "70e1dddfc81b7c785ef0fc7805a0707af6ac0862",
    "/ar-SY/chunk-2ESXI7NW.js": "01925eede0a285ade12726570c8056bd65b50788",
    "/ar-SY/chunk-2OQBOLLM.js": "37ec659d5d43be94d9c463fc61d8a29a420b0460",
    "/ar-SY/chunk-2QBYFC2R.js": "b21b241d38af4c2bc2515c9b9c497a29eff8528c",
    "/ar-SY/chunk-2RLRAFKW.js": "94d3d981f88275d71117bd51fe2157a38c541bcc",
    "/ar-SY/chunk-3OTRSYK2.js": "497999a2c433e040a7ad0c262ad5c0fabebeb0a5",
    "/ar-SY/chunk-3TICWBDM.js": "ca841dd502e54f35a2fa08f0a3618d53962a831a",
    "/ar-SY/chunk-4BS7IIZZ.js": "c3b4e81c39fdfa541f8dffc6fad85014c0bd0e6c",
    "/ar-SY/chunk-4WMX7V6I.js": "5584596fc1310e705d8294d55386faf0a79f7577",
    "/ar-SY/chunk-56ONM2BK.js": "725ea6596d8886daaccd45b9ca1e5e0cce9c62aa",
    "/ar-SY/chunk-5A24Y7FG.js": "c399f1c7c15b1be36c0feaf74954a2cd944405c6",
    "/ar-SY/chunk-5KQRBASI.js": "1368ad24d4abcab177783514aeebb997e4a1f26c",
    "/ar-SY/chunk-5TXOOLVZ.js": "9b560db65d82efca951805a35808e3dea17d7e92",
    "/ar-SY/chunk-65XUGUD6.js": "4036a3f482519d98f2c8c4cd83c40c4d164a8bd7",
    "/ar-SY/chunk-6H3FHWRN.js": "ac66737e3dca47d084e03d4f2de87ebe65f3a0bd",
    "/ar-SY/chunk-6N6YXKEL.js": "e4f8eba49f04389da0536c5133db108c3a3b4f5c",
    "/ar-SY/chunk-6YVLM3TN.js": "3f2b4044c6d4a33a40bec9a8dad849863f99068b",
    "/ar-SY/chunk-6YXMS2BR.js": "d54e6faff738ff35e868e5436f9f29f719b5cc5a",
    "/ar-SY/chunk-74QTK57S.js": "77a222a915258be8d1e2a0b87aaafd4a858ecffd",
    "/ar-SY/chunk-77BL6AJT.js": "dd5824aee1c94bb239315933ed9687f81b927784",
    "/ar-SY/chunk-7HVFJSX6.js": "21fe2860b9df6e9fb85d2193a4a711d7787e81ad",
    "/ar-SY/chunk-7MRZL6KI.js": "6cb45b1f34e5b20dd217d9ecb240762963c19247",
    "/ar-SY/chunk-7OTI4YDK.js": "dbc3d4e113742d47e0665991194cab79192bfb4b",
    "/ar-SY/chunk-7TERTQEQ.js": "6361b748af795fe54a389888b809144c7568160f",
    "/ar-SY/chunk-7V34RKQI.js": "9139da4d5c1415a5e232c351c02f1af1b3813cc8",
    "/ar-SY/chunk-A6EBSDLT.js": "655448fbfbed4cfda2abefc80d6cb7f91eb2a608",
    "/ar-SY/chunk-AIMGTUFT.js": "aa7029f0de8a364768a6442bef750b187428fc1b",
    "/ar-SY/chunk-ANO7OEOR.js": "02a829d99f1b4d022dbc39b73705ef847ff851a1",
    "/ar-SY/chunk-ASQTODNO.js": "ae396b88b688788a682811479a572eb8422943e2",
    "/ar-SY/chunk-AXR3FHIB.js": "78b9489fd14b3eabb0bf00fc814663372963d134",
    "/ar-SY/chunk-B3FOEZVW.js": "4df5942a66754534d848bf89562cb3cfc43cc4c5",
    "/ar-SY/chunk-BHKXZLFS.js": "c382d8872e44a1937cebf1fc5fe080fb160f406e",
    "/ar-SY/chunk-BKQEWO4F.js": "ff5ac6390782213315b99e792d0cdd902252baff",
    "/ar-SY/chunk-BOILL2JJ.js": "5e3fb0547d18f1d91f49c2d04209d8a8afda538f",
    "/ar-SY/chunk-BOX7CA7M.js": "15078a013026b94c63f541fb2922e750ad5a255e",
    "/ar-SY/chunk-BU5743HF.js": "d5d356651f332a2e982921d4c73ddba9b7b7f4d8",
    "/ar-SY/chunk-BUKW6KC4.js": "27b467375a108747ad4ac74c82965de1bf4cce8d",
    "/ar-SY/chunk-BYBGHJGR.js": "3d4d17a032b794651abcc7f9cdc7ba58e15597fa",
    "/ar-SY/chunk-C6G5FDC3.js": "09ad82465939221ebbee648a30f187f1bfc43434",
    "/ar-SY/chunk-CFJSTZEI.js": "1eab75da6ad2324273d519b39b77ea239ddf58a7",
    "/ar-SY/chunk-CNHMU26L.js": "75f82ba229a8fc4bdeb8828b19724f0d87185588",
    "/ar-SY/chunk-COXKBNGP.js": "d5d0fe29628ee1d6d1cbde381431b19d34a9f3b4",
    "/ar-SY/chunk-CWSXRFA2.js": "0c25c3e0a91f5ebae001ef44d97996c0bbb96f91",
    "/ar-SY/chunk-CXB7QISW.js": "b17c62607217ec90e52bcc6736313896d3b35339",
    "/ar-SY/chunk-D6HKAENE.js": "460b5f2bc008a1857f55affd661d11c6f38e45b7",
    "/ar-SY/chunk-DDV3ZTDK.js": "2fad641583a45f74c802b76d97e2ca5def022b2d",
    "/ar-SY/chunk-EIFEKQZ5.js": "00f1ce29a20177fe04859cb234b04d2383a13872",
    "/ar-SY/chunk-EVZ2FIK2.js": "7aef4bb347d29b899a3749311792556baa2b4b71",
    "/ar-SY/chunk-EY63G5JF.js": "bc4d0b4a267810a549ea698de566495947a35c08",
    "/ar-SY/chunk-FTZQ2DLW.js": "b61a2c2e86815ff966daf64cf0d5b8f3aea02123",
    "/ar-SY/chunk-G2YTV5YP.js": "d953687695b8fe38c8c32513d105fd711592506e",
    "/ar-SY/chunk-GLKTSYN6.js": "4e2d0378da0e8f5f6ab2041ed3924232efa6f836",
    "/ar-SY/chunk-GM25OYN2.js": "5cb28c2fec64ea61068cbeaceab8cde0a567a0d0",
    "/ar-SY/chunk-GVVLUNO3.js": "6ff2ed5f6530ab7a15de38dd3be038037f364476",
    "/ar-SY/chunk-H2P7XPBZ.js": "eec378fe4f48159dd49a07938c4d7fe674061d0d",
    "/ar-SY/chunk-HW5EUJLJ.js": "a29d53c162476b7d8cb1f91fbfc2bf213b194f97",
    "/ar-SY/chunk-IHCT72VP.js": "510ef1e861a6a78a2cda12ca1603cab4e2b7a386",
    "/ar-SY/chunk-IJU5IAB6.js": "d15a02963750cda08379c35f194bb0c845feef5c",
    "/ar-SY/chunk-J3R4INTN.js": "d4973a4df3f9dab87d606b7ed8c632897ac43620",
    "/ar-SY/chunk-JFU4W3LU.js": "a2a0a5cbb2f8123cf286901a422c4f783048a79b",
    "/ar-SY/chunk-JKWIZ5GL.js": "55f04be560467003aab1ca81d73fbeeb4aa19358",
    "/ar-SY/chunk-JSCEI2V4.js": "b9e117d9549c545d52fdb5f127340e93cc14048e",
    "/ar-SY/chunk-JSLQP7DR.js": "54433de0207efeb1699c2875352ee88d7ba047df",
    "/ar-SY/chunk-K2OVNSCM.js": "62dc3eb22379e5502b35dfc16f9e6f19ae0f4da7",
    "/ar-SY/chunk-K2S4YDTN.js": "94cfbcc22cfe24fabec6ac761ba1b1a1011c2396",
    "/ar-SY/chunk-K3CPYGZA.js": "7ab837df61a9788f208e39aa373436fed4778787",
    "/ar-SY/chunk-KELWJGI4.js": "49c9c4e0f8fb4c24cf3e11b931d85026fa8ad0ac",
    "/ar-SY/chunk-KEQWPQHD.js": "617a8fdd55a545490ceb3819ff50253cc57f0210",
    "/ar-SY/chunk-LY65NDSL.js": "a6f51e1bfcfca3eb5e4185ee4873b5604697a169",
    "/ar-SY/chunk-M4AIK4I3.js": "d4fae06b62cef09fe27ca211100b12c8c9aceab9",
    "/ar-SY/chunk-MG4IU3IR.js": "9078ec084f602fe73477f1ebed6c7aeed8ab0d1f",
    "/ar-SY/chunk-MJWPWJKC.js": "10f14d9f8f7e425d737ea671a822d36d53390612",
    "/ar-SY/chunk-ML6BNME4.js": "84dbe7179ae72070072a92efa3d958fa715e01b8",
    "/ar-SY/chunk-MQJH4F46.js": "7e664c2f74cb9eae00d715a6989986536a9cdabc",
    "/ar-SY/chunk-MQRGCQ3S.js": "96780a7fe65eb7c16fa87c3482519105e0a43dbc",
    "/ar-SY/chunk-MS3W46DA.js": "94e6cfb30c3e7b357c27191c216526d20229ce3a",
    "/ar-SY/chunk-MXDHFMHH.js": "af7e5d3e823ef8e1fd807015b5dd23b53d6e766f",
    "/ar-SY/chunk-MY6KCFOE.js": "67bbcf430572018bbadf2ac2bfb17bc10ed6606f",
    "/ar-SY/chunk-N3OI26PY.js": "6a6d42bcc163a37fea13595c94630d7964a8ddbf",
    "/ar-SY/chunk-N4UNFT77.js": "d92474365f942b1e8af4b8780450562e639f39cd",
    "/ar-SY/chunk-N6QQS7LB.js": "a347b793c13a58ac1b67d6882b48a8fbd5da3c11",
    "/ar-SY/chunk-NKXXNLKV.js": "14eb170b9be1f6f653ba1ee5a95a111137f5629e",
    "/ar-SY/chunk-ODDAAWLR.js": "b4a8217af44cf478ac51abc114d0aeff7ddc19a0",
    "/ar-SY/chunk-P6UXWRH3.js": "6dea643ecbda0f519f7ea989b14521e302d43708",
    "/ar-SY/chunk-PER6NRC5.js": "af3c978659ff2c4b108799858d8d3ebcecf7d67a",
    "/ar-SY/chunk-PM6FEDNM.js": "9086d0444d2a8e8930d3957cc7ac36b5dc4c502e",
    "/ar-SY/chunk-PMOT4F4H.js": "40e9cdca6fe116806c5624032a33223ab4371659",
    "/ar-SY/chunk-QQVDK5OV.js": "de05dcf621ae92abb4d597a1a97a8aaccf5fa0c3",
    "/ar-SY/chunk-RAM4WGO4.js": "6fd3b5801c79e6169eae6ac690c185d952a5b975",
    "/ar-SY/chunk-RHOUE5MX.js": "015ae75af53c1f705754629d8974bb5ab4379d0b",
    "/ar-SY/chunk-RWLY27NV.js": "0d2695167c85c96524e7fa073928dd9a58c40bd5",
    "/ar-SY/chunk-S5NKVWMB.js": "980907d4fc7a223f6134dc1b24531aee3bef3438",
    "/ar-SY/chunk-S7OYWSAY.js": "24c88c86ba99458b099006ca697a06dd8aa0ff75",
    "/ar-SY/chunk-SHFMPPN3.js": "2b886fd7772ff2a44e91b9aec8cb642d0a545933",
    "/ar-SY/chunk-SJX7X5WF.js": "34dcdebb1442ea4bedf2c9169249c08bfb1893d0",
    "/ar-SY/chunk-SMEONY5R.js": "b6cc2450b400ad0aa3167259397dc6c3b37ce12b",
    "/ar-SY/chunk-SMSWA6Y3.js": "f8c4a2d423ae952ba727417039c92311f753d487",
    "/ar-SY/chunk-TGGWUGCF.js": "75506592e2a983321660f57074cb571cb0a18f10",
    "/ar-SY/chunk-TKF7E2YR.js": "6124ec9c9fe8d1069d0184ce2dd8b4961dba21ee",
    "/ar-SY/chunk-U4N237WM.js": "4889b5138883a85cdb6dc532968eff51b219b960",
    "/ar-SY/chunk-U72UV7FI.js": "13a6d4daa180dc4d6dd17d71f50afa5205c95cd6",
    "/ar-SY/chunk-UA7SCKX3.js": "ca1076734b280a35348bf58c2aef83029da0dfa6",
    "/ar-SY/chunk-UOJQ5IBE.js": "604a775fe3968e34f0ec21f95ef25d9c4c39eb92",
    "/ar-SY/chunk-VARUJZUG.js": "77076f5d442f057571efb893a1837362473da259",
    "/ar-SY/chunk-VK6LNBMX.js": "a45156f2064da5929eaae41ecdf89a859c16acdb",
    "/ar-SY/chunk-VOQPTL3E.js": "71d293edaf02d223e643443e84bbe1d0a6df9f48",
    "/ar-SY/chunk-VQ5NJNCO.js": "5180c6423411ebdfe1dc242851aaa8e064abfe4c",
    "/ar-SY/chunk-VTI3DU76.js": "8a37b405a4f99c462e363ab97fdcb85f19211fd5",
    "/ar-SY/chunk-W7FXRVMY.js": "040fb242f553a47b878681b5511218efcc3c243e",
    "/ar-SY/chunk-WDDGOVXW.js": "74c6af15fbcf9f905a1f192876fafa68f5c38c5d",
    "/ar-SY/chunk-WOGJSFX2.js": "c234c7a40177b61c1545e5b3b49918b99ee4bda0",
    "/ar-SY/chunk-WX4XW32G.js": "7977998080fca3d9a0fc0b9c324cc993f6aac8d3",
    "/ar-SY/chunk-XYHX3JVK.js": "93fc5e1ec1c39878f6c73d6dbe475217fb97ce4e",
    "/ar-SY/chunk-Y6HRGFPG.js": "191c13372f906171360138608bee824982341f04",
    "/ar-SY/chunk-YFTDYVS3.js": "27f455b9b0e5ae14e8737242c7905b0afa4ed99c",
    "/ar-SY/chunk-ZBZOYA56.js": "7e1102368ac9fc90b2bc5fae6c7d30d24232c0c5",
    "/ar-SY/chunk-ZCB5W4HJ.js": "7b2b68a936f18c5e9bd69a63ee1cc6335a687d1f",
    "/ar-SY/chunk-ZKMPTML6.js": "190ee657967562318fbc2f29f167a695ea9388a6",
    "/ar-SY/chunk-ZLCKFGW7.js": "65915e225629159f5fce968e8844012dd611ad51",
    "/ar-SY/chunk-ZONUYZGY.js": "affafd9a811826feee18787801b55b2e4285800c",
    "/ar-SY/chunk-ZU4H4WCR.js": "1abe125b2735338d5f95e7113b626d9989e6d136",
    "/ar-SY/chunk-ZWRLN3HF.js": "b74d55e9c9331efe67ef7b0db03a307628a2aa76",
    "/ar-SY/favicon.ico": "bbefa69b9b502990d6a87b7dc4e011d257cb503b",
    "/ar-SY/index.html": "d9075d1b91fafd407eebab5eefa7b5f7ab2e568f",
    "/ar-SY/main-YGXHIUDT.js": "9d81f6ca2a49115e7178fb1fabc531c8a59a338c",
    "/ar-SY/manifest.webmanifest": "1703674a33e7c4ce1d8441ca39f9cc79fd6c91a0",
    "/ar-SY/polyfills-EEFQP6KM.js": "2c3e3bf6b26ecf76d4e39013d5f16a5297f4e7bd",
    "/ar-SY/styles-JC6X7JJ2.css": "a8c2cc6f8a2152a84b54abfd29cfad1b7df84e94"
  },
  "navigationUrls": [
    {
      "positive": true,
      "regex": "^\\/.*$"
    },
    {
      "positive": false,
      "regex": "^\\/(?:.+\\/)?[^/]*\\.[^/]*$"
    },
    {
      "positive": false,
      "regex": "^\\/(?:.+\\/)?[^/]*__[^/]*$"
    },
    {
      "positive": false,
      "regex": "^\\/(?:.+\\/)?[^/]*__[^/]*\\/.*$"
    }
  ],
  "navigationRequestStrategy": "performance"
}