{
  "configVersion": 1,
  "timestamp": 1712550271584,
  "index": "/ar-SY/index.html",
  "assetGroups": [
    {
      "name": "app",
      "installMode": "prefetch",
      "updateMode": "prefetch",
      "cacheQueryOptions": {
        "ignoreVary": true
      },
      "urls": [
        "/ar-SY/chunk-2645KM3G.js",
        "/ar-SY/chunk-2AOXHGPY.js",
        "/ar-SY/chunk-2KSXYJ2I.js",
        "/ar-SY/chunk-2NI7UYLR.js",
        "/ar-SY/chunk-3HJO43YT.js",
        "/ar-SY/chunk-3ZKJEUO4.js",
        "/ar-SY/chunk-42FLNDSV.js",
        "/ar-SY/chunk-45FF6DZ6.js",
        "/ar-SY/chunk-4UPN7KGY.js",
        "/ar-SY/chunk-4ZEOSM2S.js",
        "/ar-SY/chunk-55WNZ6UL.js",
        "/ar-SY/chunk-5J3KAS4U.js",
        "/ar-SY/chunk-6K2TUM35.js",
        "/ar-SY/chunk-7AYCK3V4.js",
        "/ar-SY/chunk-A4PWIGE4.js",
        "/ar-SY/chunk-AJSOGB7E.js",
        "/ar-SY/chunk-ARHG3HPB.js",
        "/ar-SY/chunk-BMRBIOPX.js",
        "/ar-SY/chunk-BNCFLTIN.js",
        "/ar-SY/chunk-BPSQNXP6.js",
        "/ar-SY/chunk-BT2TUCSX.js",
        "/ar-SY/chunk-CAQYSNED.js",
        "/ar-SY/chunk-CHYDGBN6.js",
        "/ar-SY/chunk-CMOZHKF7.js",
        "/ar-SY/chunk-CNC353E5.js",
        "/ar-SY/chunk-CWEN2IOM.js",
        "/ar-SY/chunk-D6XBGGEX.js",
        "/ar-SY/chunk-DDTQY3A6.js",
        "/ar-SY/chunk-DGPBMQMD.js",
        "/ar-SY/chunk-DVJMNNGS.js",
        "/ar-SY/chunk-EBQ5VNT2.js",
        "/ar-SY/chunk-ETALXWQT.js",
        "/ar-SY/chunk-FAAG2S7J.js",
        "/ar-SY/chunk-FCGGP46A.js",
        "/ar-SY/chunk-FDR4LRE7.js",
        "/ar-SY/chunk-FO6L74EZ.js",
        "/ar-SY/chunk-FRDS3MXL.js",
        "/ar-SY/chunk-FWPBQVHP.js",
        "/ar-SY/chunk-GT42TELI.js",
        "/ar-SY/chunk-GVLCV7JQ.js",
        "/ar-SY/chunk-HDJBEY5M.js",
        "/ar-SY/chunk-HUYPW546.js",
        "/ar-SY/chunk-HXDA7ZQB.js",
        "/ar-SY/chunk-ICZ3WQY5.js",
        "/ar-SY/chunk-IQ3TWIRX.js",
        "/ar-SY/chunk-ISGSVELC.js",
        "/ar-SY/chunk-JHIO5ZJT.js",
        "/ar-SY/chunk-JULEQ3X3.js",
        "/ar-SY/chunk-JXTUR5TK.js",
        "/ar-SY/chunk-K22M36D5.js",
        "/ar-SY/chunk-KHT6DQAE.js",
        "/ar-SY/chunk-KJLXE6OW.js",
        "/ar-SY/chunk-KLYJP2XX.js",
        "/ar-SY/chunk-KRHPQHQL.js",
        "/ar-SY/chunk-KWXPSVAP.js",
        "/ar-SY/chunk-LGHSQHOU.js",
        "/ar-SY/chunk-LW56SAW2.js",
        "/ar-SY/chunk-MCH3RVOG.js",
        "/ar-SY/chunk-MEEKG3B7.js",
        "/ar-SY/chunk-MO4NVWKW.js",
        "/ar-SY/chunk-NADWVHF7.js",
        "/ar-SY/chunk-NNTCFL54.js",
        "/ar-SY/chunk-NZAUTDGQ.js",
        "/ar-SY/chunk-OBLA7NMA.js",
        "/ar-SY/chunk-OVYMSJG4.js",
        "/ar-SY/chunk-PO4PALZI.js",
        "/ar-SY/chunk-PRJX2JAQ.js",
        "/ar-SY/chunk-PSTFR276.js",
        "/ar-SY/chunk-RBDFU2IS.js",
        "/ar-SY/chunk-RH6M2N5K.js",
        "/ar-SY/chunk-RJL5AG56.js",
        "/ar-SY/chunk-RLCUPFKX.js",
        "/ar-SY/chunk-RO553O4B.js",
        "/ar-SY/chunk-RRUANXYA.js",
        "/ar-SY/chunk-RSRLAWGT.js",
        "/ar-SY/chunk-RVITHZCN.js",
        "/ar-SY/chunk-RX4QSF3O.js",
        "/ar-SY/chunk-UDYVQMSU.js",
        "/ar-SY/chunk-UK4TGSGS.js",
        "/ar-SY/chunk-URZ63WEK.js",
        "/ar-SY/chunk-UTAEFVA5.js",
        "/ar-SY/chunk-UXWDAJ7U.js",
        "/ar-SY/chunk-VHEILY3D.js",
        "/ar-SY/chunk-VKKLIJN4.js",
        "/ar-SY/chunk-WCKPVAQG.js",
        "/ar-SY/chunk-WEDXSEMQ.js",
        "/ar-SY/chunk-Y24FFV4B.js",
        "/ar-SY/chunk-YG45P3ML.js",
        "/ar-SY/chunk-Z2XY5XFX.js",
        "/ar-SY/chunk-ZYP33TOD.js",
        "/ar-SY/favicon.ico",
        "/ar-SY/index.html",
        "/ar-SY/main-7MX5MQ2L.js",
        "/ar-SY/polyfills-BA37E6WE.js",
        "/ar-SY/styles-CVHFDDWN.css"
      ],
      "patterns": []
    },
    {
      "name": "assets",
      "installMode": "lazy",
      "updateMode": "prefetch",
      "cacheQueryOptions": {
        "ignoreVary": true
      },
      "urls": [
        "/ar-SY/assets/icons/icon-1024x1024.png",
        "/ar-SY/assets/icons/icon-128x128.png",
        "/ar-SY/assets/icons/icon-144x144.png",
        "/ar-SY/assets/icons/icon-152x152.png",
        "/ar-SY/assets/icons/icon-192x192.png",
        "/ar-SY/assets/icons/icon-384x384.png",
        "/ar-SY/assets/icons/icon-512x512.png",
        "/ar-SY/assets/icons/icon-72x72.png",
        "/ar-SY/assets/icons/icon-96x96.png",
        "/ar-SY/assets/icons/logo.svg",
        "/ar-SY/assets/manifest.webmanifest",
        "/ar-SY/assets/routes.json",
        "/ar-SY/assets/silent-check-sso.html"
      ],
      "patterns": []
    }
  ],
  "dataGroups": [],
  "hashTable": {
    "/ar-SY/assets/icons/icon-1024x1024.png": "343f28cb3c76d72b107a2fefb10b969669c01be6",
    "/ar-SY/assets/icons/icon-128x128.png": "6fdefbdc892cf0a2e2978ec20c62adc78563ddcc",
    "/ar-SY/assets/icons/icon-144x144.png": "f5fa8ccd5a2f5446385359ed421392a3cb9a1f4c",
    "/ar-SY/assets/icons/icon-152x152.png": "75f380ad5e5402d022a212ae3b9fc8993c43bf28",
    "/ar-SY/assets/icons/icon-192x192.png": "8ee9e04e6f2c92021c43f6a4155c03d7b17a77cc",
    "/ar-SY/assets/icons/icon-384x384.png": "4e3fd5c70359fa04e2effad67fe75f5b97b0e267",
    "/ar-SY/assets/icons/icon-512x512.png": "0814ffa04b16bace18b263b5eaadf74ad93c66f8",
    "/ar-SY/assets/icons/icon-72x72.png": "f0c683910c6b082da8ad3f0b0a15cdc0011d3cf1",
    "/ar-SY/assets/icons/icon-96x96.png": "c7e674d0d4bec68e9690db445f3834848c61650e",
    "/ar-SY/assets/icons/logo.svg": "68e0aaf67e3dfda3fea05691634081ab400c0b19",
    "/ar-SY/assets/manifest.webmanifest": "18888e6394966cf7930b621a9079f9704941d07a",
    "/ar-SY/assets/routes.json": "59902287b279810a236faa16df2e4fc779f41c01",
    "/ar-SY/assets/silent-check-sso.html": "245bcb1f39394815c4686c8f03820f8d52c46e9c",
    "/ar-SY/chunk-2645KM3G.js": "95a8666d0c47ea671af9680036ab796f3427b509",
    "/ar-SY/chunk-2AOXHGPY.js": "7c690f681fb530a1d40ab7150a3cab69948891ae",
    "/ar-SY/chunk-2KSXYJ2I.js": "f493167bba3ed24ad67fa742b264a1296746d29c",
    "/ar-SY/chunk-2NI7UYLR.js": "10cdb77f34102255c0abf1b4d7ec485ee685c84e",
    "/ar-SY/chunk-3HJO43YT.js": "67cdc90eacf017db6806187fc0916d8f7091261e",
    "/ar-SY/chunk-3ZKJEUO4.js": "2d1c94b0976fb08b90033403162ef6f18243765e",
    "/ar-SY/chunk-42FLNDSV.js": "cb01757a089efd4302fd31d5a4455e2065dcdb45",
    "/ar-SY/chunk-45FF6DZ6.js": "233edcad14724d5ab5fceb00b78dd3ea3681f5ca",
    "/ar-SY/chunk-4UPN7KGY.js": "3395d4f68dcbcb4dbbf0c64a92a53f0b4e44c91e",
    "/ar-SY/chunk-4ZEOSM2S.js": "d6e8357874bb8d4cb36793a53f6b691696e6d9a1",
    "/ar-SY/chunk-55WNZ6UL.js": "56406741f3e2475a11d2442df76f3e3f25f9662b",
    "/ar-SY/chunk-5J3KAS4U.js": "7510fe103e6c5b9a7f3eb4b9320673769bda3572",
    "/ar-SY/chunk-6K2TUM35.js": "96ded5b96f673885950fb789a710f77732ec6971",
    "/ar-SY/chunk-7AYCK3V4.js": "0f7b549491d8d118d074fc4f74e7646953b883ba",
    "/ar-SY/chunk-A4PWIGE4.js": "569816c32ad3f8dcc4cd24c0ba7ebb1ac9efdbc9",
    "/ar-SY/chunk-AJSOGB7E.js": "be3bcc64e670b920eebbbfc12b9beed8cfe82f2d",
    "/ar-SY/chunk-ARHG3HPB.js": "563a82e7458c040d7d1ac67cfbb81cae89b42bf6",
    "/ar-SY/chunk-BMRBIOPX.js": "c763c68140f8374608356e9a0fc0cd3d44bc2569",
    "/ar-SY/chunk-BNCFLTIN.js": "1311bbf8371735fd8cb042cb0e6c0bfb6776b5f4",
    "/ar-SY/chunk-BPSQNXP6.js": "4fabeb04780ace8b91a2940f44fc15ee170bf5d1",
    "/ar-SY/chunk-BT2TUCSX.js": "1ff34dc27b99a7455d69b1f2f9418c055d807bac",
    "/ar-SY/chunk-CAQYSNED.js": "1995161c1ec4ff470aa28fee1a77ba384f439f4d",
    "/ar-SY/chunk-CHYDGBN6.js": "a0ffb2318d4bffa001a7ad72de290b8e2d1e19ff",
    "/ar-SY/chunk-CMOZHKF7.js": "d96fc697416d306c03c48343a32d22b62773d9fa",
    "/ar-SY/chunk-CNC353E5.js": "f2cfe993c9503a27540a275454bb1f7c52472bb8",
    "/ar-SY/chunk-CWEN2IOM.js": "394bfd95e6df306ff6131cbf2bbc7e34e1f9c611",
    "/ar-SY/chunk-D6XBGGEX.js": "f6d5ce21bb0749cd3bcefc39aa798f693447e904",
    "/ar-SY/chunk-DDTQY3A6.js": "eaaf423a099e16fe55f49ed15a2652f6b4b11306",
    "/ar-SY/chunk-DGPBMQMD.js": "80405cfc366c5356f6ced645e130db424e4bb868",
    "/ar-SY/chunk-DVJMNNGS.js": "eb8d8714cb23e4821f3634237f30c5d9932c852f",
    "/ar-SY/chunk-EBQ5VNT2.js": "9e2f18848be3666122166e325f87a9cb303f2801",
    "/ar-SY/chunk-ETALXWQT.js": "e39a97c7b8f17c6e2ff937a2107f2ff3f3e1e21d",
    "/ar-SY/chunk-FAAG2S7J.js": "994065c2d23de72a65bcbcd48be83c497a56021f",
    "/ar-SY/chunk-FCGGP46A.js": "e3ac667642cbd41a62ef02994807ec13e50876e2",
    "/ar-SY/chunk-FDR4LRE7.js": "5beb51dfbe1f6cc9792dd27b7ce5ef4f0b9573ec",
    "/ar-SY/chunk-FO6L74EZ.js": "c178f5de1dd185cce4a26339ab3a6c7487254819",
    "/ar-SY/chunk-FRDS3MXL.js": "dc46ba5ea34286aefcea264fb75e60cf11f390eb",
    "/ar-SY/chunk-FWPBQVHP.js": "61416b3bbb403a5d1f99751419d29a67a0719aac",
    "/ar-SY/chunk-GT42TELI.js": "8a2ac1405b10b8ca4affeff7e39b1f493ca492d9",
    "/ar-SY/chunk-GVLCV7JQ.js": "5843cc6a35155575f4e5effb1f1770694413e2a0",
    "/ar-SY/chunk-HDJBEY5M.js": "5e89bb6cbfa51733ffe3de47bc1dd76bf04f10c3",
    "/ar-SY/chunk-HUYPW546.js": "9f30d90dd84ca7909f4d313c9a37429729593106",
    "/ar-SY/chunk-HXDA7ZQB.js": "c3b2c3c9911a5cca1ce78df0f90add5327ffdbb5",
    "/ar-SY/chunk-ICZ3WQY5.js": "d7d95204e91ef9d84a85b796ff29ad1fee0a46bb",
    "/ar-SY/chunk-IQ3TWIRX.js": "54246a54cccfd817c09e75df5296183903127f11",
    "/ar-SY/chunk-ISGSVELC.js": "e518a8a9e07101ae7a14b3ccf611b3dc193e0b7d",
    "/ar-SY/chunk-JHIO5ZJT.js": "569fa78cc809cb0a2568641220349358ddad8439",
    "/ar-SY/chunk-JULEQ3X3.js": "9391d205757e3da9bddafb74eb13895882930425",
    "/ar-SY/chunk-JXTUR5TK.js": "f9a997c0664ac37b50b0f74510e316080a070df4",
    "/ar-SY/chunk-K22M36D5.js": "349e73650e7346169d1ab9dce5de01652e47c12d",
    "/ar-SY/chunk-KHT6DQAE.js": "d17e233e8821967b2ea99726893f79cf2fa969b0",
    "/ar-SY/chunk-KJLXE6OW.js": "d7f06deb4bfa59d2f2dfca5b77e8696421a963af",
    "/ar-SY/chunk-KLYJP2XX.js": "16c4e905cc5ac8d79c385f728de61ab497dddfa6",
    "/ar-SY/chunk-KRHPQHQL.js": "6f33511b03b7537554a97f18b645a4072e181fd7",
    "/ar-SY/chunk-KWXPSVAP.js": "935b45bc44cb2bdf55b373c2fb4ab973c9535c09",
    "/ar-SY/chunk-LGHSQHOU.js": "5af000e975e40f85571ec2ccfdeeff31405a7df3",
    "/ar-SY/chunk-LW56SAW2.js": "001b588f104e363aab0d566cbe5cb7a52c68a7ce",
    "/ar-SY/chunk-MCH3RVOG.js": "75bc13bc87ab20806489afa3ddb323efe7ad705a",
    "/ar-SY/chunk-MEEKG3B7.js": "505a01b3590ca395601ce134896bdfe198ef0d8c",
    "/ar-SY/chunk-MO4NVWKW.js": "0f49d7809bc43e1c158cec8fe5015bee504912e9",
    "/ar-SY/chunk-NADWVHF7.js": "e4e0e0a9110e29c37bccdfaa77f2c4898b07e1e3",
    "/ar-SY/chunk-NNTCFL54.js": "97cf62e86e7364076711e1006588e573fa2b38bc",
    "/ar-SY/chunk-NZAUTDGQ.js": "baf951c7a9174ad0f359806633a1f93d27579245",
    "/ar-SY/chunk-OBLA7NMA.js": "137d9f76a30913d0fc65b6f0c27e85d8dd074aa5",
    "/ar-SY/chunk-OVYMSJG4.js": "c221aa0bd2cb00dfff62cdb0ce1e1a343ff9255e",
    "/ar-SY/chunk-PO4PALZI.js": "2e73a61454112663f0ca7899741871ff5989a6a0",
    "/ar-SY/chunk-PRJX2JAQ.js": "7948b35f41469f08175f8ac76b9ab7a90ba18c70",
    "/ar-SY/chunk-PSTFR276.js": "93c41b1ba9761d16880f0feb1322ad1a08888acf",
    "/ar-SY/chunk-RBDFU2IS.js": "f91340fd18b6910b48bba64460d7f79bb5e0d239",
    "/ar-SY/chunk-RH6M2N5K.js": "60819aeb1852da9a0e0fd17d74b48213719c5a91",
    "/ar-SY/chunk-RJL5AG56.js": "a28fc487de5802f69f027befca66a9b367143d80",
    "/ar-SY/chunk-RLCUPFKX.js": "f71ab2bd6431795ccafcb714eeda0b93e1a7118c",
    "/ar-SY/chunk-RO553O4B.js": "329336c291e9ee59b42af68a7d5153aae13c1a2c",
    "/ar-SY/chunk-RRUANXYA.js": "7b914529462bb4049dad5c0196bd9e2147fe5f67",
    "/ar-SY/chunk-RSRLAWGT.js": "18fe2030d1092cf0ddf6c8d5cd1cb2ef6ff433bd",
    "/ar-SY/chunk-RVITHZCN.js": "f68086f856d6e3bb9f6c1e4b31cd9016a038a88f",
    "/ar-SY/chunk-RX4QSF3O.js": "347c93e29e1cb2c75277ad56fe1bcb08e749a16d",
    "/ar-SY/chunk-UDYVQMSU.js": "26938ba7206d46869fb43ca46a1dac9dec3b9eb3",
    "/ar-SY/chunk-UK4TGSGS.js": "dda3bccd2406bb85072b7b016b03a36553fb69b5",
    "/ar-SY/chunk-URZ63WEK.js": "5589974220634effc90a8c1b501f36afc2b2f2ee",
    "/ar-SY/chunk-UTAEFVA5.js": "771d30a01f332da1cc6811a71f319230de617ea9",
    "/ar-SY/chunk-UXWDAJ7U.js": "1174f4ee011f4172323bcf2baccd7177d5758213",
    "/ar-SY/chunk-VHEILY3D.js": "6ed96f549ee70d053e4bb9676842c525f92f7591",
    "/ar-SY/chunk-VKKLIJN4.js": "d9dbc6151a9d31290d36f3c02f55ebd1d57fa1cb",
    "/ar-SY/chunk-WCKPVAQG.js": "4d5e5aecd47f4f316a6ec5de22b5843c16b6102d",
    "/ar-SY/chunk-WEDXSEMQ.js": "862a4cf2adb143cfc553d4474b1c3aa83cf2a819",
    "/ar-SY/chunk-Y24FFV4B.js": "8249ed0d76cc177f90e80a16fa7f1e87858c4e71",
    "/ar-SY/chunk-YG45P3ML.js": "91b93584c62ab1aa9948a172b3d76eb06acafc9b",
    "/ar-SY/chunk-Z2XY5XFX.js": "60831f793c4c44391ce83a2c1bb69bb5fc0cf442",
    "/ar-SY/chunk-ZYP33TOD.js": "c5ae06e585c140a0449169eeeb191441e8699d9a",
    "/ar-SY/favicon.ico": "bbefa69b9b502990d6a87b7dc4e011d257cb503b",
    "/ar-SY/index.html": "473ecb3f7852c7b9da7eca6b99b164ef76872ca7",
    "/ar-SY/main-7MX5MQ2L.js": "ef65a7bb1d942bed7dea24547996befd43d80a7f",
    "/ar-SY/polyfills-BA37E6WE.js": "7eba78cada04012c1c3ad65a9d7a7b50e6b19fd7",
    "/ar-SY/styles-CVHFDDWN.css": "c2d8d0ef7943561677fbb9afbc86641229672602"
  },
  "navigationUrls": [
    {
      "positive": true,
      "regex": "^\\/.*$"
    },
    {
      "positive": false,
      "regex": "^\\/(?:.+\\/)?[^/]*\\.[^/]*$"
    },
    {
      "positive": false,
      "regex": "^\\/(?:.+\\/)?[^/]*__[^/]*$"
    },
    {
      "positive": false,
      "regex": "^\\/(?:.+\\/)?[^/]*__[^/]*\\/.*$"
    }
  ],
  "navigationRequestStrategy": "performance"
}