{
  "configVersion": 1,
  "timestamp": 1712541952303,
  "index": "/en-US/index.html",
  "assetGroups": [
    {
      "name": "app",
      "installMode": "prefetch",
      "updateMode": "prefetch",
      "cacheQueryOptions": {
        "ignoreVary": true
      },
      "urls": [
        "/en-US/chunk-2FKSSAOI.js",
        "/en-US/chunk-2QMTEXGC.js",
        "/en-US/chunk-2S55VDIC.js",
        "/en-US/chunk-3CQ3G5CK.js",
        "/en-US/chunk-3NQDVLWU.js",
        "/en-US/chunk-3OXXEMBL.js",
        "/en-US/chunk-4BWAJUVX.js",
        "/en-US/chunk-4ZWA537Q.js",
        "/en-US/chunk-53DPKMHY.js",
        "/en-US/chunk-5NISDYJS.js",
        "/en-US/chunk-6DBZBKH4.js",
        "/en-US/chunk-6HLHJ2RD.js",
        "/en-US/chunk-6HUWPTXM.js",
        "/en-US/chunk-6LP2TE76.js",
        "/en-US/chunk-6NMRUJRJ.js",
        "/en-US/chunk-6PSFIBBT.js",
        "/en-US/chunk-6Q3DZWIV.js",
        "/en-US/chunk-7C7C66EE.js",
        "/en-US/chunk-7TAQOFIY.js",
        "/en-US/chunk-A2LHBOYL.js",
        "/en-US/chunk-ABRM2GT6.js",
        "/en-US/chunk-AWXW6CYA.js",
        "/en-US/chunk-BFHVC5V7.js",
        "/en-US/chunk-BJRGIEI5.js",
        "/en-US/chunk-CBC4KNAJ.js",
        "/en-US/chunk-CDVQ6UJU.js",
        "/en-US/chunk-CGJ4GPZG.js",
        "/en-US/chunk-CMSL7LBW.js",
        "/en-US/chunk-D3NT54NN.js",
        "/en-US/chunk-D4QTPFJ2.js",
        "/en-US/chunk-DLGIBLHK.js",
        "/en-US/chunk-DMOIYEBY.js",
        "/en-US/chunk-EH32H2MW.js",
        "/en-US/chunk-FFNU3AWA.js",
        "/en-US/chunk-FWOK47VW.js",
        "/en-US/chunk-GQOBDHQR.js",
        "/en-US/chunk-I24UTXLZ.js",
        "/en-US/chunk-I3QQHH5O.js",
        "/en-US/chunk-I6ASTK35.js",
        "/en-US/chunk-IORIBAA2.js",
        "/en-US/chunk-J4LWPMO3.js",
        "/en-US/chunk-JBGKD76Q.js",
        "/en-US/chunk-JPW6LE5W.js",
        "/en-US/chunk-KCMFR3MQ.js",
        "/en-US/chunk-KF6DHOCZ.js",
        "/en-US/chunk-KIFUQV5X.js",
        "/en-US/chunk-KZOFHLIP.js",
        "/en-US/chunk-LJPEJUBS.js",
        "/en-US/chunk-LNYDQNET.js",
        "/en-US/chunk-LZTLSUJQ.js",
        "/en-US/chunk-M6Q4BQFC.js",
        "/en-US/chunk-MBPCVHQ7.js",
        "/en-US/chunk-N6KZS5RJ.js",
        "/en-US/chunk-NQ5NCW7X.js",
        "/en-US/chunk-OGBWXWCJ.js",
        "/en-US/chunk-OHZ3HCBX.js",
        "/en-US/chunk-OK3P2RMO.js",
        "/en-US/chunk-OWCKJTVU.js",
        "/en-US/chunk-PKAJYHCP.js",
        "/en-US/chunk-QGU4CJ7G.js",
        "/en-US/chunk-R2UAEGG5.js",
        "/en-US/chunk-R5NYEDXS.js",
        "/en-US/chunk-RB37AKVD.js",
        "/en-US/chunk-REAKUCX3.js",
        "/en-US/chunk-RKKUZHEH.js",
        "/en-US/chunk-ROJ3JEDL.js",
        "/en-US/chunk-RRKF6G3N.js",
        "/en-US/chunk-RTZSOC2S.js",
        "/en-US/chunk-SANRGM2R.js",
        "/en-US/chunk-SCLNOAMO.js",
        "/en-US/chunk-SIYMNY6C.js",
        "/en-US/chunk-SLLS724A.js",
        "/en-US/chunk-TX6UKCUL.js",
        "/en-US/chunk-UATRIOKT.js",
        "/en-US/chunk-UKCMRQHL.js",
        "/en-US/chunk-UP5YQRAM.js",
        "/en-US/chunk-VMMZ7HGS.js",
        "/en-US/chunk-W5E5CJ52.js",
        "/en-US/chunk-W6YD2IA6.js",
        "/en-US/chunk-W7XPWCGR.js",
        "/en-US/chunk-WZE6PEND.js",
        "/en-US/chunk-XB4UZXWY.js",
        "/en-US/chunk-XIQQFK4Y.js",
        "/en-US/chunk-XJ7RKG32.js",
        "/en-US/chunk-Z4HKUGBO.js",
        "/en-US/chunk-ZEB57KTN.js",
        "/en-US/chunk-ZJZ5HM5O.js",
        "/en-US/chunk-ZLLYVBKM.js",
        "/en-US/chunk-ZSP7HO3U.js",
        "/en-US/chunk-ZU4T4IY7.js",
        "/en-US/favicon.ico",
        "/en-US/index.html",
        "/en-US/main-PODTR7MX.js",
        "/en-US/polyfills-Z72NJEXS.js",
        "/en-US/styles-CVHFDDWN.css"
      ],
      "patterns": []
    },
    {
      "name": "assets",
      "installMode": "lazy",
      "updateMode": "prefetch",
      "cacheQueryOptions": {
        "ignoreVary": true
      },
      "urls": [
        "/en-US/assets/icons/icon-1024x1024.png",
        "/en-US/assets/icons/icon-128x128.png",
        "/en-US/assets/icons/icon-144x144.png",
        "/en-US/assets/icons/icon-152x152.png",
        "/en-US/assets/icons/icon-192x192.png",
        "/en-US/assets/icons/icon-384x384.png",
        "/en-US/assets/icons/icon-512x512.png",
        "/en-US/assets/icons/icon-72x72.png",
        "/en-US/assets/icons/icon-96x96.png",
        "/en-US/assets/icons/logo.svg",
        "/en-US/assets/manifest.webmanifest",
        "/en-US/assets/routes.json",
        "/en-US/assets/silent-check-sso.html"
      ],
      "patterns": []
    }
  ],
  "dataGroups": [],
  "hashTable": {
    "/en-US/assets/icons/icon-1024x1024.png": "343f28cb3c76d72b107a2fefb10b969669c01be6",
    "/en-US/assets/icons/icon-128x128.png": "6fdefbdc892cf0a2e2978ec20c62adc78563ddcc",
    "/en-US/assets/icons/icon-144x144.png": "f5fa8ccd5a2f5446385359ed421392a3cb9a1f4c",
    "/en-US/assets/icons/icon-152x152.png": "75f380ad5e5402d022a212ae3b9fc8993c43bf28",
    "/en-US/assets/icons/icon-192x192.png": "8ee9e04e6f2c92021c43f6a4155c03d7b17a77cc",
    "/en-US/assets/icons/icon-384x384.png": "4e3fd5c70359fa04e2effad67fe75f5b97b0e267",
    "/en-US/assets/icons/icon-512x512.png": "0814ffa04b16bace18b263b5eaadf74ad93c66f8",
    "/en-US/assets/icons/icon-72x72.png": "f0c683910c6b082da8ad3f0b0a15cdc0011d3cf1",
    "/en-US/assets/icons/icon-96x96.png": "c7e674d0d4bec68e9690db445f3834848c61650e",
    "/en-US/assets/icons/logo.svg": "68e0aaf67e3dfda3fea05691634081ab400c0b19",
    "/en-US/assets/manifest.webmanifest": "18888e6394966cf7930b621a9079f9704941d07a",
    "/en-US/assets/routes.json": "59902287b279810a236faa16df2e4fc779f41c01",
    "/en-US/assets/silent-check-sso.html": "245bcb1f39394815c4686c8f03820f8d52c46e9c",
    "/en-US/chunk-2FKSSAOI.js": "7ef94f697121e8e2db457dcc89615b17b0e5c0dc",
    "/en-US/chunk-2QMTEXGC.js": "c2c5d86912f470d65f1a0370b650f5d14418820e",
    "/en-US/chunk-2S55VDIC.js": "62c9082eb8aa517b62f93479daf49c01240b96fc",
    "/en-US/chunk-3CQ3G5CK.js": "742a4b2cd4d264caaf20bf816801e72f955f20af",
    "/en-US/chunk-3NQDVLWU.js": "0a69b4dcb4bb2580009333783bd770cfffe1c91e",
    "/en-US/chunk-3OXXEMBL.js": "9b65b0938ce31549dca1bae2fd6c97351682867b",
    "/en-US/chunk-4BWAJUVX.js": "19a60377c0345e7265e9095c25d6d4e5baa2a167",
    "/en-US/chunk-4ZWA537Q.js": "1af2fda11835cb4ab403a749e8e0b1e8e7410515",
    "/en-US/chunk-53DPKMHY.js": "7c6786ba912eb4d97016a8a8248ca061bef27aa4",
    "/en-US/chunk-5NISDYJS.js": "1a2079347cdf93636c733feb11e33ad31fc25dfa",
    "/en-US/chunk-6DBZBKH4.js": "8770516a324dbf193035f5fc64ab95cfec483de6",
    "/en-US/chunk-6HLHJ2RD.js": "0754d0512af5c13489356f7626a4b46dc7831995",
    "/en-US/chunk-6HUWPTXM.js": "84c2f581a12e00e21665275022d26d7ee1d69c8b",
    "/en-US/chunk-6LP2TE76.js": "77ff8a3ece90d687b240fddcab6b4542a4d76621",
    "/en-US/chunk-6NMRUJRJ.js": "3b211665b5d1c0e90911a935379cdc3ac76ebd68",
    "/en-US/chunk-6PSFIBBT.js": "2e65f7f0b98346d5b996d827127723ac44bfb76c",
    "/en-US/chunk-6Q3DZWIV.js": "ffa4a7012a018b1281666c4086696f8261dc302f",
    "/en-US/chunk-7C7C66EE.js": "712bf28fba6b8d0dc6cf7165c47f68d7c75941ae",
    "/en-US/chunk-7TAQOFIY.js": "5845c4953468c0f85c31c998d381bbdf1b7054e1",
    "/en-US/chunk-A2LHBOYL.js": "57eeb6faa4260d0938489d312dd8db81f0ec845d",
    "/en-US/chunk-ABRM2GT6.js": "c767ae045b50083673a38ab9d8cfa976b1b4975e",
    "/en-US/chunk-AWXW6CYA.js": "e8f242c71e65e18bb630aea0748ce720a3650681",
    "/en-US/chunk-BFHVC5V7.js": "677caf46b3511d21cc37595d0a191e4c1762b7e2",
    "/en-US/chunk-BJRGIEI5.js": "e587e85f90bc37e767b8053e0e727e0cfd855a00",
    "/en-US/chunk-CBC4KNAJ.js": "de9c95f91c9286ae82d0befbaa95219612ab12b8",
    "/en-US/chunk-CDVQ6UJU.js": "1a8e1df86edc1e6c3ff17c71f53eedad0dac22b3",
    "/en-US/chunk-CGJ4GPZG.js": "815b542ad13d7fbfb2b1eeb158695efeaa579d13",
    "/en-US/chunk-CMSL7LBW.js": "859b4158584488e492243454c12e37b42ecae3ed",
    "/en-US/chunk-D3NT54NN.js": "3cdeced593e1352821b765bd0e7c2f03763a74ba",
    "/en-US/chunk-D4QTPFJ2.js": "15807fe575021920a67ba7fe58a298aa8b3bb44c",
    "/en-US/chunk-DLGIBLHK.js": "31e0067a6497e5e34f087c8953aa76ab29f7e98e",
    "/en-US/chunk-DMOIYEBY.js": "ca3e80209554f5f899a88242b0f22d3462b06d2f",
    "/en-US/chunk-EH32H2MW.js": "28ff59d36b7edf3556e3a5f261750d87dd0bbbac",
    "/en-US/chunk-FFNU3AWA.js": "d99fb61f8f176790b5479519984c7e1cb0a35fc5",
    "/en-US/chunk-FWOK47VW.js": "b43ecba17fe71642e91c1f76379ace89e13a726c",
    "/en-US/chunk-GQOBDHQR.js": "41abfb4ae86ddbb12cd66cdd16866347b561a2a9",
    "/en-US/chunk-I24UTXLZ.js": "d41bb66f987115c8f4532b1a997de624b24d6921",
    "/en-US/chunk-I3QQHH5O.js": "3f468a5d57d002568ea47dbe1c6b23126bf47cc1",
    "/en-US/chunk-I6ASTK35.js": "6e01eefbb723d54f5afc0e37448bb6d47f5d68c6",
    "/en-US/chunk-IORIBAA2.js": "6b6530dcbf5cc37c0927bce8089eca202c27f133",
    "/en-US/chunk-J4LWPMO3.js": "4e3fdd788200b42cd09bedfa68e491f6ef9c7c57",
    "/en-US/chunk-JBGKD76Q.js": "5b6730ff342fc4d37d599847b39c830c0f358cfb",
    "/en-US/chunk-JPW6LE5W.js": "4c281697844c96ef5ddbb415030dac7b1c7fc1ff",
    "/en-US/chunk-KCMFR3MQ.js": "393e87411bb5b3aa0a5bb75e156f45b4ec197076",
    "/en-US/chunk-KF6DHOCZ.js": "271ac86681ac6484b008355c6238d0de52b977f8",
    "/en-US/chunk-KIFUQV5X.js": "1fa472052ddeb6b617184b52ccc93abf6d751896",
    "/en-US/chunk-KZOFHLIP.js": "ee7e0560081aef34cad84bf40fbaed7b26d357e0",
    "/en-US/chunk-LJPEJUBS.js": "7b37602054a40b5f01908f97f28e56deb6c0e5b4",
    "/en-US/chunk-LNYDQNET.js": "3646a744c8dfdb261ea5cf2fb34926fa8b7d5a0c",
    "/en-US/chunk-LZTLSUJQ.js": "fab2989c277ad650500d15bd1655a5278fe88cad",
    "/en-US/chunk-M6Q4BQFC.js": "ca2a5f27efe3f571e1057c8d803e1c81ddc547db",
    "/en-US/chunk-MBPCVHQ7.js": "366d232f68d0fe5e76fd9cb9deb95f7c588b5c7c",
    "/en-US/chunk-N6KZS5RJ.js": "b8ad81eebbf813ac16e477ae82166b2bbe9a5027",
    "/en-US/chunk-NQ5NCW7X.js": "1a20cfaa5f548f441eacfed1a2b0125857c151aa",
    "/en-US/chunk-OGBWXWCJ.js": "274974103d3d298d557cae8ddba72d966f7c508a",
    "/en-US/chunk-OHZ3HCBX.js": "f8d7cd6cced75e332704b9a0b823ef2429f8841a",
    "/en-US/chunk-OK3P2RMO.js": "fd70511361b377527da9082998370f5125745851",
    "/en-US/chunk-OWCKJTVU.js": "9825ea5a4c0b6c844bf6b0c244887cbb676b496f",
    "/en-US/chunk-PKAJYHCP.js": "07c1941866810aa4b1a166b9d622994197dce521",
    "/en-US/chunk-QGU4CJ7G.js": "7b0a73310935b8b64b40e253d0e696e3601906d5",
    "/en-US/chunk-R2UAEGG5.js": "3637cb1ad19fa1ab3afa9ecfd0ba6e85b88f6759",
    "/en-US/chunk-R5NYEDXS.js": "3bddf702a8ef702e8a267b5f03cddb91fcd30ac1",
    "/en-US/chunk-RB37AKVD.js": "9b0a06b53af909a1426e555b75d63bdddc1f84e1",
    "/en-US/chunk-REAKUCX3.js": "402e1f34e58ac3c88a8a0de7b92523c7968c8c54",
    "/en-US/chunk-RKKUZHEH.js": "127125b3f10ffe3e3676dd54f5b43b04964466f2",
    "/en-US/chunk-ROJ3JEDL.js": "e1735afc9ea5fc18299da97d52eaaba4569f1863",
    "/en-US/chunk-RRKF6G3N.js": "b3c5c80613615aac7121d7a3e4de5e6ccf87fb7f",
    "/en-US/chunk-RTZSOC2S.js": "01d0fd7d59faee3d10ebebecc45d89177590f0af",
    "/en-US/chunk-SANRGM2R.js": "fe59dd250a2332deda2a29ddc6d171ce0dcb99c9",
    "/en-US/chunk-SCLNOAMO.js": "7003de6abe5c81e756c2c4d0b1f1b335b3da04ba",
    "/en-US/chunk-SIYMNY6C.js": "373c68342e411929b05ef9a379bbdba6cebfa8e7",
    "/en-US/chunk-SLLS724A.js": "4eebd7e052ff2cbe923d2b953912a71bde4f38e9",
    "/en-US/chunk-TX6UKCUL.js": "76691e75626640967040bf8792f256997a0f8149",
    "/en-US/chunk-UATRIOKT.js": "2407100b4d78b5bc016c46afa0e9545219ad64cb",
    "/en-US/chunk-UKCMRQHL.js": "feae269511e6d0b0bbe90ae3f75d57e7d3cf2f4e",
    "/en-US/chunk-UP5YQRAM.js": "fc4a58610c7c97941aa81c402968f562292960ac",
    "/en-US/chunk-VMMZ7HGS.js": "8c04084183c56d5546c04c8901027a7f8ffe3ee8",
    "/en-US/chunk-W5E5CJ52.js": "3982e8067f6ab49301fa570396911da9579fbb5c",
    "/en-US/chunk-W6YD2IA6.js": "9c68d101f1250e4a876398161b511712c60b84cc",
    "/en-US/chunk-W7XPWCGR.js": "d3ec37d3c1c773a421ba769a5314e328c88083a1",
    "/en-US/chunk-WZE6PEND.js": "3d6228ed104d7ff4bbdbb15aa02ead54ac99f442",
    "/en-US/chunk-XB4UZXWY.js": "1048861811a6f7a0637526974834cb9e409fb579",
    "/en-US/chunk-XIQQFK4Y.js": "be6960ca79ba730892928927e2b5a729ecd79494",
    "/en-US/chunk-XJ7RKG32.js": "ba361b87522903b23de7ac30b83c08dfdd3a7b7c",
    "/en-US/chunk-Z4HKUGBO.js": "954ad699e20a8a3b9f6931c4331ebc9e77dea0c6",
    "/en-US/chunk-ZEB57KTN.js": "d87b2df61f7f4e53461dc776bc5523b29cc5f405",
    "/en-US/chunk-ZJZ5HM5O.js": "0baa7da965bd34a690662542f3def953209cd9dc",
    "/en-US/chunk-ZLLYVBKM.js": "c84cca9c82db85e7974758207626bd5c34d1198f",
    "/en-US/chunk-ZSP7HO3U.js": "77ec2923262cd14a775c7a9bce68ef7c53e81969",
    "/en-US/chunk-ZU4T4IY7.js": "b9488be9eac800f4bdb9ef7b0fe947bf2c9cc4c7",
    "/en-US/favicon.ico": "bbefa69b9b502990d6a87b7dc4e011d257cb503b",
    "/en-US/index.html": "5bfd369442da794898ea4760267cc83080534281",
    "/en-US/main-PODTR7MX.js": "0b17fffe88da80ed0653f43c125def27b7798edd",
    "/en-US/polyfills-Z72NJEXS.js": "f039ac9182a269418b589f23b71d4a0b638a9d35",
    "/en-US/styles-CVHFDDWN.css": "c2d8d0ef7943561677fbb9afbc86641229672602"
  },
  "navigationUrls": [
    {
      "positive": true,
      "regex": "^\\/.*$"
    },
    {
      "positive": false,
      "regex": "^\\/(?:.+\\/)?[^/]*\\.[^/]*$"
    },
    {
      "positive": false,
      "regex": "^\\/(?:.+\\/)?[^/]*__[^/]*$"
    },
    {
      "positive": false,
      "regex": "^\\/(?:.+\\/)?[^/]*__[^/]*\\/.*$"
    }
  ],
  "navigationRequestStrategy": "performance"
}