{
  "configVersion": 1,
  "timestamp": 1722342912228,
  "index": "/en-US/index.html",
  "assetGroups": [
    {
      "name": "app",
      "installMode": "prefetch",
      "updateMode": "prefetch",
      "cacheQueryOptions": {
        "ignoreVary": true
      },
      "urls": [
        "/en-US/chunk-24L4I6SV.js",
        "/en-US/chunk-2PMBRQGX.js",
        "/en-US/chunk-2UTMVH6A.js",
        "/en-US/chunk-3VUWZCPX.js",
        "/en-US/chunk-4KJ7JOBN.js",
        "/en-US/chunk-4MUZI5HK.js",
        "/en-US/chunk-4NVYPK46.js",
        "/en-US/chunk-4TLR5CU3.js",
        "/en-US/chunk-4VWLEJ4P.js",
        "/en-US/chunk-527OBFO6.js",
        "/en-US/chunk-55YB23JU.js",
        "/en-US/chunk-57EQYW4O.js",
        "/en-US/chunk-5HAJP4H4.js",
        "/en-US/chunk-5O54AGUL.js",
        "/en-US/chunk-5TZ2K576.js",
        "/en-US/chunk-5ZTWELIO.js",
        "/en-US/chunk-6I6QP7OO.js",
        "/en-US/chunk-72FHVNNU.js",
        "/en-US/chunk-7H2423YX.js",
        "/en-US/chunk-7MC5NWL4.js",
        "/en-US/chunk-7XP3UIEP.js",
        "/en-US/chunk-ARJDRL2D.js",
        "/en-US/chunk-ASNO3K42.js",
        "/en-US/chunk-BEVK4ODJ.js",
        "/en-US/chunk-BKHI6ZH6.js",
        "/en-US/chunk-CFBSPEDC.js",
        "/en-US/chunk-CLHUVMRT.js",
        "/en-US/chunk-COMQXV4W.js",
        "/en-US/chunk-CP2DMO7M.js",
        "/en-US/chunk-CT6OEJN7.js",
        "/en-US/chunk-CUF6JG73.js",
        "/en-US/chunk-CXCVSTK4.js",
        "/en-US/chunk-DC2TKIII.js",
        "/en-US/chunk-DJCJT4SO.js",
        "/en-US/chunk-EECBSBLF.js",
        "/en-US/chunk-EJH6FQAG.js",
        "/en-US/chunk-EQ7LNM5G.js",
        "/en-US/chunk-ER5KDHHX.js",
        "/en-US/chunk-EY27VXMI.js",
        "/en-US/chunk-EY745HI5.js",
        "/en-US/chunk-FBQL5NQC.js",
        "/en-US/chunk-FZSAKOSX.js",
        "/en-US/chunk-G5EETSCD.js",
        "/en-US/chunk-G5LT37XW.js",
        "/en-US/chunk-GDELZHLZ.js",
        "/en-US/chunk-GHZFV73K.js",
        "/en-US/chunk-GO5Q2O4Z.js",
        "/en-US/chunk-H7B2FXCV.js",
        "/en-US/chunk-HF6ZLKY7.js",
        "/en-US/chunk-HNVQMQ2A.js",
        "/en-US/chunk-HQIALI45.js",
        "/en-US/chunk-HR4N2ICJ.js",
        "/en-US/chunk-HUMV6CZ7.js",
        "/en-US/chunk-I2UE2ZW3.js",
        "/en-US/chunk-IGQXTHNA.js",
        "/en-US/chunk-II4AO3JV.js",
        "/en-US/chunk-ILMMVNTQ.js",
        "/en-US/chunk-KVT2Y44B.js",
        "/en-US/chunk-L4AIUAS4.js",
        "/en-US/chunk-LEDCB6OE.js",
        "/en-US/chunk-LNHKWV2Q.js",
        "/en-US/chunk-LQE3BAMR.js",
        "/en-US/chunk-M7N2T4RI.js",
        "/en-US/chunk-MA43TKOS.js",
        "/en-US/chunk-MANQGQ5S.js",
        "/en-US/chunk-MOKWSACW.js",
        "/en-US/chunk-MRQOP6PR.js",
        "/en-US/chunk-MUH2IUTC.js",
        "/en-US/chunk-MUR7RDT4.js",
        "/en-US/chunk-MYK76I3Y.js",
        "/en-US/chunk-NLG5J4BV.js",
        "/en-US/chunk-NUOXDBV4.js",
        "/en-US/chunk-NVMJT3SR.js",
        "/en-US/chunk-NXYBY2DC.js",
        "/en-US/chunk-OA72MJAL.js",
        "/en-US/chunk-OD2PBDQL.js",
        "/en-US/chunk-OKL2XGIL.js",
        "/en-US/chunk-OXQDAN4H.js",
        "/en-US/chunk-OYKRF4EQ.js",
        "/en-US/chunk-PJPJU545.js",
        "/en-US/chunk-PMGZB256.js",
        "/en-US/chunk-PSX66ZGI.js",
        "/en-US/chunk-Q53FQPCV.js",
        "/en-US/chunk-QCCR3EP4.js",
        "/en-US/chunk-QOPKBTR3.js",
        "/en-US/chunk-R7DCD7ZI.js",
        "/en-US/chunk-RGMACJ3F.js",
        "/en-US/chunk-RQY53CVQ.js",
        "/en-US/chunk-RS5EUCW5.js",
        "/en-US/chunk-RTULAJFL.js",
        "/en-US/chunk-S24KQKNZ.js",
        "/en-US/chunk-SV7OQSW7.js",
        "/en-US/chunk-TBEHEJF6.js",
        "/en-US/chunk-TDQJWVPF.js",
        "/en-US/chunk-THKQOVJQ.js",
        "/en-US/chunk-TLDGN6JY.js",
        "/en-US/chunk-UBUNO3NI.js",
        "/en-US/chunk-UKANWANQ.js",
        "/en-US/chunk-UZ3BV3VI.js",
        "/en-US/chunk-V5DZRW4C.js",
        "/en-US/chunk-V6C4Z4TM.js",
        "/en-US/chunk-W7XNY4ZM.js",
        "/en-US/chunk-WP4QADEO.js",
        "/en-US/chunk-WZNJXRSX.js",
        "/en-US/chunk-XU6WJOFR.js",
        "/en-US/chunk-YWT2EA4M.js",
        "/en-US/chunk-ZCG62LHU.js",
        "/en-US/favicon.ico",
        "/en-US/index.html",
        "/en-US/main-GJEMLVXJ.js",
        "/en-US/manifest.webmanifest",
        "/en-US/polyfills-3LVWV6FS.js",
        "/en-US/styles-OOWRGS3A.css"
      ],
      "patterns": []
    },
    {
      "name": "assets",
      "installMode": "lazy",
      "updateMode": "prefetch",
      "cacheQueryOptions": {
        "ignoreVary": true
      },
      "urls": [
        "/en-US/assets/icons/icon-1024x1024.png",
        "/en-US/assets/icons/icon-128x128.png",
        "/en-US/assets/icons/icon-144x144.png",
        "/en-US/assets/icons/icon-152x152.png",
        "/en-US/assets/icons/icon-192x192.png",
        "/en-US/assets/icons/icon-384x384.png",
        "/en-US/assets/icons/icon-512x512.png",
        "/en-US/assets/icons/icon-72x72.png",
        "/en-US/assets/icons/icon-96x96.png",
        "/en-US/assets/icons/logo.svg",
        "/en-US/assets/routes.json",
        "/en-US/assets/silent-check-sso.html"
      ],
      "patterns": []
    }
  ],
  "dataGroups": [],
  "hashTable": {
    "/en-US/assets/icons/icon-1024x1024.png": "343f28cb3c76d72b107a2fefb10b969669c01be6",
    "/en-US/assets/icons/icon-128x128.png": "6fdefbdc892cf0a2e2978ec20c62adc78563ddcc",
    "/en-US/assets/icons/icon-144x144.png": "f5fa8ccd5a2f5446385359ed421392a3cb9a1f4c",
    "/en-US/assets/icons/icon-152x152.png": "75f380ad5e5402d022a212ae3b9fc8993c43bf28",
    "/en-US/assets/icons/icon-192x192.png": "8ee9e04e6f2c92021c43f6a4155c03d7b17a77cc",
    "/en-US/assets/icons/icon-384x384.png": "4e3fd5c70359fa04e2effad67fe75f5b97b0e267",
    "/en-US/assets/icons/icon-512x512.png": "0814ffa04b16bace18b263b5eaadf74ad93c66f8",
    "/en-US/assets/icons/icon-72x72.png": "f0c683910c6b082da8ad3f0b0a15cdc0011d3cf1",
    "/en-US/assets/icons/icon-96x96.png": "c7e674d0d4bec68e9690db445f3834848c61650e",
    "/en-US/assets/icons/logo.svg": "68e0aaf67e3dfda3fea05691634081ab400c0b19",
    "/en-US/assets/routes.json": "59902287b279810a236faa16df2e4fc779f41c01",
    "/en-US/assets/silent-check-sso.html": "245bcb1f39394815c4686c8f03820f8d52c46e9c",
    "/en-US/chunk-24L4I6SV.js": "4a39e35b1bdd918669eb54fbdd2463f666009ff9",
    "/en-US/chunk-2PMBRQGX.js": "36ee7cf70a69d5677d83def50de84c205dd1358e",
    "/en-US/chunk-2UTMVH6A.js": "45000f244332f96d272cd69ba0e28bac696a842b",
    "/en-US/chunk-3VUWZCPX.js": "b0221dfd4c146929e0702e9d3844ea4f59824884",
    "/en-US/chunk-4KJ7JOBN.js": "9a891b332a47c82d3676f2fdfe76638ae6120313",
    "/en-US/chunk-4MUZI5HK.js": "77acd4349bd9cdafd68f1c0689a07f5ad5cd449f",
    "/en-US/chunk-4NVYPK46.js": "dc484f549b5a821a74325d82303810c53abbc196",
    "/en-US/chunk-4TLR5CU3.js": "0ee792b65f482b9c8fc34090a01804170073060b",
    "/en-US/chunk-4VWLEJ4P.js": "f527a22f1fb676a98f037b950bce679ee230b8d1",
    "/en-US/chunk-527OBFO6.js": "27e52741c96d5e6fce35025f13eeddfad5c94950",
    "/en-US/chunk-55YB23JU.js": "512767b17aed95241d812084eb657eae2b5bb8b0",
    "/en-US/chunk-57EQYW4O.js": "49fe30d9a97488418f79ba96edb8b5f319ff9a93",
    "/en-US/chunk-5HAJP4H4.js": "7cabd77954b948cbe8755cb8300e1668ef75269e",
    "/en-US/chunk-5O54AGUL.js": "5b67b3aa65f74dc088a13eaab63bb645cf693b99",
    "/en-US/chunk-5TZ2K576.js": "85e611e9b05c834f8e57894e78d78ad298763b43",
    "/en-US/chunk-5ZTWELIO.js": "6b3743958c006cb72b4068c1a543c2e4527f8be8",
    "/en-US/chunk-6I6QP7OO.js": "4e30ac5e6b9379732a209ff2eae10c6e4a9d9ce3",
    "/en-US/chunk-72FHVNNU.js": "283dd450878b7bb80d9cc1f0f2c95c9c36584c5c",
    "/en-US/chunk-7H2423YX.js": "cad2e729ff82e041b563459321e725f9bbd08d10",
    "/en-US/chunk-7MC5NWL4.js": "f4d5852bbcc6acaec96e752940a4b816f4f8e539",
    "/en-US/chunk-7XP3UIEP.js": "bc34d340b8e791d0161b7cdc193e62596badf135",
    "/en-US/chunk-ARJDRL2D.js": "a146e8e6766714d63fde6834a9f4e65c1effbccd",
    "/en-US/chunk-ASNO3K42.js": "e04c73ca84736e0ff25c38faa076faaa51cf495d",
    "/en-US/chunk-BEVK4ODJ.js": "2022593b50b8e610e07734c4fb697cb40f40d8ea",
    "/en-US/chunk-BKHI6ZH6.js": "b612b70d065bb0a1c91f6066bbe02f4368251f45",
    "/en-US/chunk-CFBSPEDC.js": "8631a2ad996fa6e26e08f240c16732bfbb405686",
    "/en-US/chunk-CLHUVMRT.js": "165534a939dc92a814aafd69d80f1f6058929f6f",
    "/en-US/chunk-COMQXV4W.js": "e9c2d08bef6b81ec7ad8796a9e9d98206c883085",
    "/en-US/chunk-CP2DMO7M.js": "01c095b697ce51ba3e34b4a691e5b1e4e2463e3a",
    "/en-US/chunk-CT6OEJN7.js": "80f0fdac79c438efa2f84f8fc57fd803b0e85601",
    "/en-US/chunk-CUF6JG73.js": "cea7519b3ebf078bf3049ba4291ae29e1c2e3367",
    "/en-US/chunk-CXCVSTK4.js": "edeb7cd49678f36afd2b536bfd120448f5149563",
    "/en-US/chunk-DC2TKIII.js": "f77750268b29c96399fa7c8de88c16d8e2320796",
    "/en-US/chunk-DJCJT4SO.js": "f893da84a1c0ebf4b5cf5fcbdab7c8b4c69f1825",
    "/en-US/chunk-EECBSBLF.js": "3cc5e89db00028143612851908a6f7362f74eb5a",
    "/en-US/chunk-EJH6FQAG.js": "f27e11d6309796563c4ac755dc6bc88b00d399ef",
    "/en-US/chunk-EQ7LNM5G.js": "eddb3d9a2fd6396aab13da08f2d47208bcfbaec1",
    "/en-US/chunk-ER5KDHHX.js": "4d5dfa4e44e64c85449ce1dfddbf11ca7a977f63",
    "/en-US/chunk-EY27VXMI.js": "72bd878c96c2694a41a4ab47dcd86f68c0e849bd",
    "/en-US/chunk-EY745HI5.js": "4d4c968b117b4ddec5d03602c453cbadfc907e5e",
    "/en-US/chunk-FBQL5NQC.js": "805cddfe52a5af642a7c7ff159b8ae4f31f5d936",
    "/en-US/chunk-FZSAKOSX.js": "231d048cd566b1ba02649d0efde9bc6c36b793b4",
    "/en-US/chunk-G5EETSCD.js": "2028809b2dc83bf09de2241d462decf406033359",
    "/en-US/chunk-G5LT37XW.js": "2e543ef36e62c0a422c32a1a273d374b1d105b12",
    "/en-US/chunk-GDELZHLZ.js": "f23a59f38ed40ebf6a958a84c09010487ac58ff1",
    "/en-US/chunk-GHZFV73K.js": "0fcc109df601c81ed0a6377ec879ec4e5405dde4",
    "/en-US/chunk-GO5Q2O4Z.js": "9a94d555213fa3d2d01afcaae473474d5340b372",
    "/en-US/chunk-H7B2FXCV.js": "68e5c3286e3f7fb6fca4a3c3955e042faf010985",
    "/en-US/chunk-HF6ZLKY7.js": "403fd012d6b5b933bff5951b25b223288cd7c2bb",
    "/en-US/chunk-HNVQMQ2A.js": "e9387c5c644dfa62910a01602980030d528e0a43",
    "/en-US/chunk-HQIALI45.js": "871d7f00e023118ed643fb44b6c3009ea82e1220",
    "/en-US/chunk-HR4N2ICJ.js": "7b3cfe07eb6cce9b2300afeaa2686e84f3854cad",
    "/en-US/chunk-HUMV6CZ7.js": "ae283d273cb540b2a7c23416644640cf4677f483",
    "/en-US/chunk-I2UE2ZW3.js": "309cb5fb6156f7a53542d9ef225ce2665e496b33",
    "/en-US/chunk-IGQXTHNA.js": "45775e9cba4e0e0a0a05a834ae3eef71f8e5c0d1",
    "/en-US/chunk-II4AO3JV.js": "fcb9889679047a533381ea8a2fbc52605bd0cd24",
    "/en-US/chunk-ILMMVNTQ.js": "fe8e33cf14300ed6efc2991d3a37e31efcbb946c",
    "/en-US/chunk-KVT2Y44B.js": "0bdde035de891f7a87974caf50f82fd7edab986c",
    "/en-US/chunk-L4AIUAS4.js": "56420bed86f457f1e6a16bb52071ad4933e3ab6f",
    "/en-US/chunk-LEDCB6OE.js": "21743ba7a2e5c1ef573cdbb153f771bbd15b7679",
    "/en-US/chunk-LNHKWV2Q.js": "d4c87a263fdce9b78ee54e7e54e2170be1ec2b43",
    "/en-US/chunk-LQE3BAMR.js": "06a39bf4dad63ebc716df387948bf584570227e7",
    "/en-US/chunk-M7N2T4RI.js": "b27acbf22536ea4f0919550c227d4bf5a6f71ce1",
    "/en-US/chunk-MA43TKOS.js": "9b3812682b2d14dc5f47f60753063087283110d9",
    "/en-US/chunk-MANQGQ5S.js": "60d3eda30f46d7b2485dd44bc42b10c13f8993ed",
    "/en-US/chunk-MOKWSACW.js": "2d71de10e989a3c1297f4dd8e56d6d2c15bc8219",
    "/en-US/chunk-MRQOP6PR.js": "5b9f282ff4a6a3b8c16fac1ed48109fba98cbccb",
    "/en-US/chunk-MUH2IUTC.js": "b4774879bac6474a5e9f129005370c9348213a83",
    "/en-US/chunk-MUR7RDT4.js": "f9b90afa449bacbefd685d1fe956353bff471f0e",
    "/en-US/chunk-MYK76I3Y.js": "6210108601f93000832774220cc2abdcc08ff20c",
    "/en-US/chunk-NLG5J4BV.js": "41b29d30c874277a272f40f0c20c56311c735490",
    "/en-US/chunk-NUOXDBV4.js": "669b83932ee5dba84f4a8b87a18f9e35ae3b24aa",
    "/en-US/chunk-NVMJT3SR.js": "d0824a82668c16d7cc7d0d11c3534dcc8a1c835a",
    "/en-US/chunk-NXYBY2DC.js": "24e269eeee1ed2c0dc6f724871ff6b74ffc069b0",
    "/en-US/chunk-OA72MJAL.js": "5168b3eb23841303af3801744450eaed9262ca83",
    "/en-US/chunk-OD2PBDQL.js": "02069dcf7bbe0f9be919bc7e349f72a31ce7e51d",
    "/en-US/chunk-OKL2XGIL.js": "d09480bc3b43c03c72a5dde03abf5f17ee501b07",
    "/en-US/chunk-OXQDAN4H.js": "a58840918c45ba3804ff098a68c269a05b5c3554",
    "/en-US/chunk-OYKRF4EQ.js": "5de0e224d48fc7522e031cc4ded0640290f9c1ab",
    "/en-US/chunk-PJPJU545.js": "7aadd76d508e31133ce8a4c3e496e396200bb800",
    "/en-US/chunk-PMGZB256.js": "cc6b14b6c7696cff9b869e4b7feaa1e9c121fd93",
    "/en-US/chunk-PSX66ZGI.js": "27626b154253a0f097c2954f8bb56984e840fadd",
    "/en-US/chunk-Q53FQPCV.js": "14240250dbd63b9e01572eaf41a70ffdb6159330",
    "/en-US/chunk-QCCR3EP4.js": "0a6654b9d3bafa3d3feb9b1bb3e40b75e1a14c19",
    "/en-US/chunk-QOPKBTR3.js": "f91107ae38b35658497c7a4e5f382c886dde4994",
    "/en-US/chunk-R7DCD7ZI.js": "78c12228b3f22a53a38e32942eaaf0878594cde0",
    "/en-US/chunk-RGMACJ3F.js": "ce16f514ebe15139cace9328efb73881a2ff6397",
    "/en-US/chunk-RQY53CVQ.js": "14508c7b46ce1c136e639690029b5d71dd41ac3d",
    "/en-US/chunk-RS5EUCW5.js": "1f13ff8d960ee5e6fc63aff2bfeff12736d1afc4",
    "/en-US/chunk-RTULAJFL.js": "de1e6319fbb156c7b61fdf491b9bef04aab176fa",
    "/en-US/chunk-S24KQKNZ.js": "a41665dde14a96df7e645bc8c5074fc8cb24a22f",
    "/en-US/chunk-SV7OQSW7.js": "fbfa5881e91df51281de63a587210a03325da6d0",
    "/en-US/chunk-TBEHEJF6.js": "5cf68670ed144054b09e268d532704c79df35f2e",
    "/en-US/chunk-TDQJWVPF.js": "79b7569c631ae1ba0b8aad4c3c4e36a87d4b8fdb",
    "/en-US/chunk-THKQOVJQ.js": "e1828cf14874e43b594868f58edab5ab42cb2d1f",
    "/en-US/chunk-TLDGN6JY.js": "b566c029574dcb487a30abd67ab197b4f3994fca",
    "/en-US/chunk-UBUNO3NI.js": "e461246e7aa56a016ad274efbf815e1f93fd1c0b",
    "/en-US/chunk-UKANWANQ.js": "60469dde1b5dd7b8842966d79aee49c49f14b68e",
    "/en-US/chunk-UZ3BV3VI.js": "61b724b2aad84ff789cd235b5cd6e409dfa67fa9",
    "/en-US/chunk-V5DZRW4C.js": "5a633905c9396828c2022fbfa44dddd7272cae0b",
    "/en-US/chunk-V6C4Z4TM.js": "0e32f45067933afffb816ce79fec1c55ff68c130",
    "/en-US/chunk-W7XNY4ZM.js": "58ff97a6e3b97dc4a0a72d598439ce250ec25a95",
    "/en-US/chunk-WP4QADEO.js": "331fb0be543c6bca009d7d7b0e9a504a24b01692",
    "/en-US/chunk-WZNJXRSX.js": "971ffc32c62b553256b48ef410ac31eac122c125",
    "/en-US/chunk-XU6WJOFR.js": "7584c98d85c3aa697233619c376aed10f063dcf4",
    "/en-US/chunk-YWT2EA4M.js": "0a1cdec4793d627aa0b3e6326b409bc14db4837d",
    "/en-US/chunk-ZCG62LHU.js": "fb0e7b914f9917db98fc77c5f15cb84f9d435c4b",
    "/en-US/favicon.ico": "bbefa69b9b502990d6a87b7dc4e011d257cb503b",
    "/en-US/index.html": "2b903798b2f63d69a9bc8f0feccf3fbde7401e69",
    "/en-US/main-GJEMLVXJ.js": "56eade54d6041092d39581a2ca2f659afc32e09b",
    "/en-US/manifest.webmanifest": "1703674a33e7c4ce1d8441ca39f9cc79fd6c91a0",
    "/en-US/polyfills-3LVWV6FS.js": "2971bdf00cd6c88c83ec1920e5802b1e72d5fbf9",
    "/en-US/styles-OOWRGS3A.css": "8720237522f2238c815a283f0fa4af07f1b52cf3"
  },
  "navigationUrls": [
    {
      "positive": true,
      "regex": "^\\/.*$"
    },
    {
      "positive": false,
      "regex": "^\\/(?:.+\\/)?[^/]*\\.[^/]*$"
    },
    {
      "positive": false,
      "regex": "^\\/(?:.+\\/)?[^/]*__[^/]*$"
    },
    {
      "positive": false,
      "regex": "^\\/(?:.+\\/)?[^/]*__[^/]*\\/.*$"
    }
  ],
  "navigationRequestStrategy": "performance"
}