{
  "configVersion": 1,
  "timestamp": 1722917574297,
  "index": "/en-US/index.html",
  "assetGroups": [
    {
      "name": "app",
      "installMode": "prefetch",
      "updateMode": "prefetch",
      "cacheQueryOptions": {
        "ignoreVary": true
      },
      "urls": [
        "/en-US/chunk-25BISADR.js",
        "/en-US/chunk-2AKYOICX.js",
        "/en-US/chunk-2LUHYUVI.js",
        "/en-US/chunk-4DOBDNMN.js",
        "/en-US/chunk-4I3TW6N7.js",
        "/en-US/chunk-4TOHVJ3T.js",
        "/en-US/chunk-4WE7TOVA.js",
        "/en-US/chunk-4X3EEI6G.js",
        "/en-US/chunk-4ZXKVXKP.js",
        "/en-US/chunk-55762Q5S.js",
        "/en-US/chunk-5ERX2ZKK.js",
        "/en-US/chunk-6BPUQMXP.js",
        "/en-US/chunk-6EQPQJW3.js",
        "/en-US/chunk-77YYM3RF.js",
        "/en-US/chunk-7GEYLSOC.js",
        "/en-US/chunk-7GLIBPHT.js",
        "/en-US/chunk-7O3A3MFP.js",
        "/en-US/chunk-7R23LAHR.js",
        "/en-US/chunk-7WXNJPQE.js",
        "/en-US/chunk-AB47EWDE.js",
        "/en-US/chunk-AMNVKT6U.js",
        "/en-US/chunk-AS77WDL2.js",
        "/en-US/chunk-B6RMQ6SH.js",
        "/en-US/chunk-BBUHI33F.js",
        "/en-US/chunk-BC6TH3PO.js",
        "/en-US/chunk-CFQ2423C.js",
        "/en-US/chunk-CKMIAYXP.js",
        "/en-US/chunk-CP2TL4J4.js",
        "/en-US/chunk-DI6TE2V7.js",
        "/en-US/chunk-DKUXPBPK.js",
        "/en-US/chunk-DN3KK3KA.js",
        "/en-US/chunk-E34SCBYX.js",
        "/en-US/chunk-E5MJL4EQ.js",
        "/en-US/chunk-EHIKGCBK.js",
        "/en-US/chunk-EJ2N3AK4.js",
        "/en-US/chunk-ER72LNTG.js",
        "/en-US/chunk-ETAO7SFH.js",
        "/en-US/chunk-F6DO6CRO.js",
        "/en-US/chunk-FBOVBCOB.js",
        "/en-US/chunk-FMHCORPX.js",
        "/en-US/chunk-FRWCOXS4.js",
        "/en-US/chunk-GG3Z7D7G.js",
        "/en-US/chunk-GQVBMTVZ.js",
        "/en-US/chunk-H3FOOGF5.js",
        "/en-US/chunk-H3PDEY3T.js",
        "/en-US/chunk-H62JKFC3.js",
        "/en-US/chunk-HE7EGVAY.js",
        "/en-US/chunk-HENALJQ5.js",
        "/en-US/chunk-HFXM4MOX.js",
        "/en-US/chunk-HRDXMWCF.js",
        "/en-US/chunk-HWSLRHWT.js",
        "/en-US/chunk-HWVQOC2X.js",
        "/en-US/chunk-I7UQCMDJ.js",
        "/en-US/chunk-ID6V6OOS.js",
        "/en-US/chunk-ISBXWYR4.js",
        "/en-US/chunk-JHZ66CMH.js",
        "/en-US/chunk-JXJYDBQT.js",
        "/en-US/chunk-JYX4FAMI.js",
        "/en-US/chunk-KBZN5S2S.js",
        "/en-US/chunk-KCMCGJDS.js",
        "/en-US/chunk-KI4GB7L3.js",
        "/en-US/chunk-KQNVFDOS.js",
        "/en-US/chunk-KWEEKQXD.js",
        "/en-US/chunk-L6IPN3E3.js",
        "/en-US/chunk-LCFIH6IT.js",
        "/en-US/chunk-LEUFBNU5.js",
        "/en-US/chunk-LGG5C546.js",
        "/en-US/chunk-LIMIMVQY.js",
        "/en-US/chunk-LKBRM2T2.js",
        "/en-US/chunk-NE5STG6Q.js",
        "/en-US/chunk-NFB6SB3R.js",
        "/en-US/chunk-NLAQW34T.js",
        "/en-US/chunk-NR36EC3F.js",
        "/en-US/chunk-NXQ5VREG.js",
        "/en-US/chunk-OIOWUZGQ.js",
        "/en-US/chunk-ORWSIRA4.js",
        "/en-US/chunk-OYQFD5AK.js",
        "/en-US/chunk-OZV6Q74H.js",
        "/en-US/chunk-PDH4JCAS.js",
        "/en-US/chunk-PDPJ66GF.js",
        "/en-US/chunk-Q37SQ7DW.js",
        "/en-US/chunk-Q7YRED3C.js",
        "/en-US/chunk-QXFCOYDA.js",
        "/en-US/chunk-QXM4JFQV.js",
        "/en-US/chunk-QXNWOEBV.js",
        "/en-US/chunk-SIGJIEHA.js",
        "/en-US/chunk-SWRWNFV6.js",
        "/en-US/chunk-SZOKMVCT.js",
        "/en-US/chunk-TDFQ4HJR.js",
        "/en-US/chunk-TIPWNHVX.js",
        "/en-US/chunk-UGSW5MLU.js",
        "/en-US/chunk-UNB64CPV.js",
        "/en-US/chunk-UUW7EA2T.js",
        "/en-US/chunk-UXER5ZR6.js",
        "/en-US/chunk-UYYWHWBI.js",
        "/en-US/chunk-VRORGLMS.js",
        "/en-US/chunk-VWCWFRJW.js",
        "/en-US/chunk-VYM6M4IG.js",
        "/en-US/chunk-WABYONCF.js",
        "/en-US/chunk-WCUD5KKG.js",
        "/en-US/chunk-WH3JX6YX.js",
        "/en-US/chunk-WO6X2WJ6.js",
        "/en-US/chunk-XCCPTZUV.js",
        "/en-US/chunk-YKNU4QOL.js",
        "/en-US/chunk-YNHLE3XH.js",
        "/en-US/chunk-YPLVL3HC.js",
        "/en-US/chunk-Z2LVGH3F.js",
        "/en-US/chunk-ZCIDB4G7.js",
        "/en-US/chunk-ZFEV7ZY2.js",
        "/en-US/chunk-ZSZINKJW.js",
        "/en-US/chunk-ZWRT7LR5.js",
        "/en-US/favicon.ico",
        "/en-US/index.html",
        "/en-US/main-PW2B3MSC.js",
        "/en-US/manifest.webmanifest",
        "/en-US/polyfills-ARYSLKH2.js",
        "/en-US/styles-GMLS2DHJ.css"
      ],
      "patterns": []
    },
    {
      "name": "assets",
      "installMode": "lazy",
      "updateMode": "prefetch",
      "cacheQueryOptions": {
        "ignoreVary": true
      },
      "urls": [
        "/en-US/assets/icons/icon-1024x1024.png",
        "/en-US/assets/icons/icon-128x128.png",
        "/en-US/assets/icons/icon-144x144.png",
        "/en-US/assets/icons/icon-152x152.png",
        "/en-US/assets/icons/icon-192x192.png",
        "/en-US/assets/icons/icon-384x384.png",
        "/en-US/assets/icons/icon-512x512.png",
        "/en-US/assets/icons/icon-72x72.png",
        "/en-US/assets/icons/icon-96x96.png",
        "/en-US/assets/icons/logo.svg",
        "/en-US/assets/routes.json",
        "/en-US/assets/silent-check-sso.html"
      ],
      "patterns": []
    }
  ],
  "dataGroups": [],
  "hashTable": {
    "/en-US/assets/icons/icon-1024x1024.png": "343f28cb3c76d72b107a2fefb10b969669c01be6",
    "/en-US/assets/icons/icon-128x128.png": "6fdefbdc892cf0a2e2978ec20c62adc78563ddcc",
    "/en-US/assets/icons/icon-144x144.png": "f5fa8ccd5a2f5446385359ed421392a3cb9a1f4c",
    "/en-US/assets/icons/icon-152x152.png": "75f380ad5e5402d022a212ae3b9fc8993c43bf28",
    "/en-US/assets/icons/icon-192x192.png": "8ee9e04e6f2c92021c43f6a4155c03d7b17a77cc",
    "/en-US/assets/icons/icon-384x384.png": "4e3fd5c70359fa04e2effad67fe75f5b97b0e267",
    "/en-US/assets/icons/icon-512x512.png": "0814ffa04b16bace18b263b5eaadf74ad93c66f8",
    "/en-US/assets/icons/icon-72x72.png": "f0c683910c6b082da8ad3f0b0a15cdc0011d3cf1",
    "/en-US/assets/icons/icon-96x96.png": "c7e674d0d4bec68e9690db445f3834848c61650e",
    "/en-US/assets/icons/logo.svg": "68e0aaf67e3dfda3fea05691634081ab400c0b19",
    "/en-US/assets/routes.json": "59902287b279810a236faa16df2e4fc779f41c01",
    "/en-US/assets/silent-check-sso.html": "245bcb1f39394815c4686c8f03820f8d52c46e9c",
    "/en-US/chunk-25BISADR.js": "d3330177f7fb1235ee9a0fe71e696b5f7d47e192",
    "/en-US/chunk-2AKYOICX.js": "212bb5c04f33a40ac40d4b06462c66e75153c847",
    "/en-US/chunk-2LUHYUVI.js": "defa8d5de5e140830ba1a17a728478e5ce0c9cf8",
    "/en-US/chunk-4DOBDNMN.js": "0699a840867116b92d5f2f620a059b3bbc5e4169",
    "/en-US/chunk-4I3TW6N7.js": "8feeab0540563b2e99d0c7ba45a7e507b9844662",
    "/en-US/chunk-4TOHVJ3T.js": "cbb9e32f26f77a541f78ecc7c24742868e22e894",
    "/en-US/chunk-4WE7TOVA.js": "c964f97e206ab1b17a08b7dcfabbc32d23130f60",
    "/en-US/chunk-4X3EEI6G.js": "ab9c6ba3722d6a5f0d194f420490bf3d36059fb7",
    "/en-US/chunk-4ZXKVXKP.js": "20fc0bdc2d83265aa717c08bf597b1891929a2e8",
    "/en-US/chunk-55762Q5S.js": "bea93d3da9516d687fc255629664d05181ba94b8",
    "/en-US/chunk-5ERX2ZKK.js": "82559853e3f0feebc3528229ce8b335a5669d782",
    "/en-US/chunk-6BPUQMXP.js": "9def21fdfd50de7600d5f32bc1ea940b6191f691",
    "/en-US/chunk-6EQPQJW3.js": "ea9c7e622c3d015a7f08c06ac96df413de19308a",
    "/en-US/chunk-77YYM3RF.js": "889c8c04856e5589d0f0f7a996a835b222e7bec8",
    "/en-US/chunk-7GEYLSOC.js": "57f2bc640f93003c8f5c86d9a532dca8df533253",
    "/en-US/chunk-7GLIBPHT.js": "1328848c8c88caf13ac3b4a1fbbea26708fa0f24",
    "/en-US/chunk-7O3A3MFP.js": "28dbd20f5bf188284ecd07a8a0bd791817b612d6",
    "/en-US/chunk-7R23LAHR.js": "5651ccf38ec3b8e5d52c3b93afdcebf5d34db52f",
    "/en-US/chunk-7WXNJPQE.js": "8ab4f94430797137d327552ef8bd716bcf27bf41",
    "/en-US/chunk-AB47EWDE.js": "4d2e5563d469432434ea8eb9e4949f35a7f02ca4",
    "/en-US/chunk-AMNVKT6U.js": "aefe0f044bbc5901b1415920319f7e17a5d3f34e",
    "/en-US/chunk-AS77WDL2.js": "d6b8c8509a25c1e7da00b0d1981e0a62c6e4b401",
    "/en-US/chunk-B6RMQ6SH.js": "ba37cffc118ffa8eba0b0049ada4a48f0bc7aaa5",
    "/en-US/chunk-BBUHI33F.js": "a0f76905b8ff2c02c1c881595d1aa9e0c42db37c",
    "/en-US/chunk-BC6TH3PO.js": "4f660c768dc57b1d52499cfe156baa9d069ef22d",
    "/en-US/chunk-CFQ2423C.js": "a43e0e11e54ff62463825f43e26055ea1551f3a0",
    "/en-US/chunk-CKMIAYXP.js": "868255e2bc4e54154815c85620a3d2eb4bcd90d2",
    "/en-US/chunk-CP2TL4J4.js": "3a48a70090445b483a981eb3835a85781754fc44",
    "/en-US/chunk-DI6TE2V7.js": "48573679c2578881feeae95669cf8d0a8dd361bd",
    "/en-US/chunk-DKUXPBPK.js": "ddba9191cb0aa81c8592d24c0cdfb6c3074b68c9",
    "/en-US/chunk-DN3KK3KA.js": "ea5e781380f163638ae72fdd101e0b1ce160055d",
    "/en-US/chunk-E34SCBYX.js": "94e68a24d3675fdf41b76e8926eeecc92e1087d3",
    "/en-US/chunk-E5MJL4EQ.js": "b454f7590a2630fc3c79f7a4b88eeec45d25a14b",
    "/en-US/chunk-EHIKGCBK.js": "563a6ba0d93c6eda9dfb7a1295aaea95e6142a55",
    "/en-US/chunk-EJ2N3AK4.js": "86d5e2a22d9dbdd12e54573db4920b47c56cabe9",
    "/en-US/chunk-ER72LNTG.js": "f4aa76a8bae249ed9ce74f74b0c32976503f31e1",
    "/en-US/chunk-ETAO7SFH.js": "afd8e61796756060370ae1eb267522afc97da137",
    "/en-US/chunk-F6DO6CRO.js": "d46c4b231f70d67889c057667bf131b0ae85bc2e",
    "/en-US/chunk-FBOVBCOB.js": "3890bcc5c4c887a75f00f3a4cdaec23249004679",
    "/en-US/chunk-FMHCORPX.js": "592be63a3930412151c3d472814ed1bcc02bfbf9",
    "/en-US/chunk-FRWCOXS4.js": "3cb46b62edbc97d576408603a15e7f4aeace2233",
    "/en-US/chunk-GG3Z7D7G.js": "9601190563d6336a6191b87fd962b377a2219c4d",
    "/en-US/chunk-GQVBMTVZ.js": "2c5bf307ccb4dce0e2e2bfce91b718bd97f2a6aa",
    "/en-US/chunk-H3FOOGF5.js": "72fdd9ba1aac0beaf8b8a406ad8c154ffa0327a4",
    "/en-US/chunk-H3PDEY3T.js": "8c598d743ba75036d5846b17e6d9481348b2ac3c",
    "/en-US/chunk-H62JKFC3.js": "6ea5003a85e30ba4097c7341af6604362596b0e0",
    "/en-US/chunk-HE7EGVAY.js": "fa45ec1072947f8d5811e6fdd904fae9425fd4c3",
    "/en-US/chunk-HENALJQ5.js": "20503da76664a9f425abbde99430f6b9df528535",
    "/en-US/chunk-HFXM4MOX.js": "e2ee65123ffbeefe7d1d738541d91efaa8b70278",
    "/en-US/chunk-HRDXMWCF.js": "db6ff1f36b8aa628c088f5d5a1ad34906484e87f",
    "/en-US/chunk-HWSLRHWT.js": "c01b23e3212f53b7622e35ca7adc7f5816f3b6b5",
    "/en-US/chunk-HWVQOC2X.js": "aa68593cbd0b9d4680bffa1450312e304e1fdfcc",
    "/en-US/chunk-I7UQCMDJ.js": "10a8441311ad56695455f005571259166c3adb4e",
    "/en-US/chunk-ID6V6OOS.js": "adf8aa2fdedfc13d8229f9a4bae73ad68813668f",
    "/en-US/chunk-ISBXWYR4.js": "d40a3365c1fa9d01e55b8d30664321cfde8a1717",
    "/en-US/chunk-JHZ66CMH.js": "53c4d20de728b8867955d1d41811195843e0afbd",
    "/en-US/chunk-JXJYDBQT.js": "bafb5545e342e5cd76a75f17dd3c00fede42cb3a",
    "/en-US/chunk-JYX4FAMI.js": "6678a592ab69a9c8fad8dad37fa656db89b48407",
    "/en-US/chunk-KBZN5S2S.js": "ff1e8b07c5e4ce3d9a57db8676aaefd85de2032a",
    "/en-US/chunk-KCMCGJDS.js": "3093e01092f4d2f731602d700874937e74b744a8",
    "/en-US/chunk-KI4GB7L3.js": "9fc8a1b90e0022444d8827ab7927740cdb594ea1",
    "/en-US/chunk-KQNVFDOS.js": "7c47632afeafaaaa373c4f16c6f5d94c4219e3b2",
    "/en-US/chunk-KWEEKQXD.js": "36846b4f0723a448bd5dfcaa96e1094cdeba4d05",
    "/en-US/chunk-L6IPN3E3.js": "083c0e57b0044f0565ed95912ead6218587d41a0",
    "/en-US/chunk-LCFIH6IT.js": "b08a5785e659abdd624759ff0f8b6bb5f585470a",
    "/en-US/chunk-LEUFBNU5.js": "ddffcb85d9ebe28e27fdf563584ec9f495bd5477",
    "/en-US/chunk-LGG5C546.js": "5a8b92c163c9dade8dd38e75d81c0c45ce01da61",
    "/en-US/chunk-LIMIMVQY.js": "5e55c0ba7b938c3d630608e9394c3251eec14bf2",
    "/en-US/chunk-LKBRM2T2.js": "c8836c236efdece795fd2958e1b04fae9ca0f3c0",
    "/en-US/chunk-NE5STG6Q.js": "f8a74726813538c6c2ae92dde2a2762d9d2254de",
    "/en-US/chunk-NFB6SB3R.js": "10eafcff26c9ceb9fedee490e8250548a638f5c3",
    "/en-US/chunk-NLAQW34T.js": "e0bb26c457036bf9a4095f504669deabe193759a",
    "/en-US/chunk-NR36EC3F.js": "b44a814b73adb84255382211896af5185e72c4d4",
    "/en-US/chunk-NXQ5VREG.js": "764546ceddffb7d740652f1b9e551d1d2d5ecf50",
    "/en-US/chunk-OIOWUZGQ.js": "4a2a18c8db4b2b3d779c8f2b679b148ba14325d8",
    "/en-US/chunk-ORWSIRA4.js": "4bba895a41d438f4be9707c2baa9747ccc9c6f18",
    "/en-US/chunk-OYQFD5AK.js": "9c7582da06d6911c751e2c211bc3daca8269002c",
    "/en-US/chunk-OZV6Q74H.js": "b1f53653962c34be9db65b4b37794ef7ac6b0e4d",
    "/en-US/chunk-PDH4JCAS.js": "09a79069688446df9ff41ce7d366a0085b332925",
    "/en-US/chunk-PDPJ66GF.js": "e6c09ae11004c9983183d0807c975d15705acd0f",
    "/en-US/chunk-Q37SQ7DW.js": "559812accf7f5f204ebc879285e68f01047dddfa",
    "/en-US/chunk-Q7YRED3C.js": "a1987f6292cecfafb428a5dc4fe5a2947fe90fda",
    "/en-US/chunk-QXFCOYDA.js": "cd46e20c839b5d0af494b54ec4193e3729f89268",
    "/en-US/chunk-QXM4JFQV.js": "76f53d3b6fc2810a95af3ba43d5eb40169962753",
    "/en-US/chunk-QXNWOEBV.js": "0c6d3688fd75a85f84784e92d27af2c37f29f8dc",
    "/en-US/chunk-SIGJIEHA.js": "9a833f862c6e48ee7857291d9adea141bc1ae768",
    "/en-US/chunk-SWRWNFV6.js": "b112470bbe4a8166bef994f1fa2a90f5061bc95e",
    "/en-US/chunk-SZOKMVCT.js": "df80fdcbc9f89b71ee6fdce899b513db2acc0a55",
    "/en-US/chunk-TDFQ4HJR.js": "a9f6a06f47d4a40671e9647f2713de6f66bd1823",
    "/en-US/chunk-TIPWNHVX.js": "af022485154854c105768232a082527c325bb89f",
    "/en-US/chunk-UGSW5MLU.js": "a44b33c8232abc648d189eeab226e9ee1b213206",
    "/en-US/chunk-UNB64CPV.js": "cec8bebd90d13e79198c8f5ed74ea905b17d0214",
    "/en-US/chunk-UUW7EA2T.js": "e8f30752141f53ba0f18a64351d765cf4df4f43a",
    "/en-US/chunk-UXER5ZR6.js": "16af40325a88213b87eca744d426f6316ae19730",
    "/en-US/chunk-UYYWHWBI.js": "4419afa026e66cb7e8c4223bf2b2cefa1ec24da9",
    "/en-US/chunk-VRORGLMS.js": "1447ac346f4983b1c163fe2237b709143b2cd954",
    "/en-US/chunk-VWCWFRJW.js": "13f0e94c8e5613610e0967c01498515d313725a9",
    "/en-US/chunk-VYM6M4IG.js": "236d4d39e1955072cc31c942fa83399a19124308",
    "/en-US/chunk-WABYONCF.js": "405b935c2c92d9567c94237aa57ba78b049ad78d",
    "/en-US/chunk-WCUD5KKG.js": "f5cf549710738f26b8790d1fcf89ae75c65431ae",
    "/en-US/chunk-WH3JX6YX.js": "f9f9a4dbe89ce6229ec7c821db9602e7db075254",
    "/en-US/chunk-WO6X2WJ6.js": "f8dded5f20b069d406a7d5b25f3dc8469037cd9d",
    "/en-US/chunk-XCCPTZUV.js": "2f8d8dac2ce6d1f94da25f8c3ee772046ba5430d",
    "/en-US/chunk-YKNU4QOL.js": "00542516ee4726228976d32e970efe8fd81d0192",
    "/en-US/chunk-YNHLE3XH.js": "e25be3979382fdd830c13607a34d445d9084200d",
    "/en-US/chunk-YPLVL3HC.js": "9f753b16576a4865f24b136af28b713a87147aea",
    "/en-US/chunk-Z2LVGH3F.js": "b022b060de4776e7b31ba013741b5e1489ff8ac0",
    "/en-US/chunk-ZCIDB4G7.js": "b18dae6fd2de239c54a6e0ff5f8add51e56b0abb",
    "/en-US/chunk-ZFEV7ZY2.js": "b76807423d7bd95fb0a69300e3bef62354cef96a",
    "/en-US/chunk-ZSZINKJW.js": "2bc6dfd3fdf7e85f5d60cdf28c60b971f58ac03f",
    "/en-US/chunk-ZWRT7LR5.js": "b9462e3fb12e82c81bdd046499da3add61974579",
    "/en-US/favicon.ico": "bbefa69b9b502990d6a87b7dc4e011d257cb503b",
    "/en-US/index.html": "a9cb9be993e42cdfde0789431808536533681185",
    "/en-US/main-PW2B3MSC.js": "723d93f006f8dc4ecd72132cd17b2ed9cb201cd8",
    "/en-US/manifest.webmanifest": "1703674a33e7c4ce1d8441ca39f9cc79fd6c91a0",
    "/en-US/polyfills-ARYSLKH2.js": "aafc3dd110e41957303203bdee58a0aa3f587112",
    "/en-US/styles-GMLS2DHJ.css": "b519664d0938248cc1204952453d930d230be02d"
  },
  "navigationUrls": [
    {
      "positive": true,
      "regex": "^\\/.*$"
    },
    {
      "positive": false,
      "regex": "^\\/(?:.+\\/)?[^/]*\\.[^/]*$"
    },
    {
      "positive": false,
      "regex": "^\\/(?:.+\\/)?[^/]*__[^/]*$"
    },
    {
      "positive": false,
      "regex": "^\\/(?:.+\\/)?[^/]*__[^/]*\\/.*$"
    }
  ],
  "navigationRequestStrategy": "performance"
}